[{"arguments":["clang","-Wno-documentation-unknown-command","-Wno-unknown-warning-option","-Wno-unknown-pragmas","-nostdinc","-nostdinc++","-std=gnu++1z","-Wall","-Wextra","-Wextra","-fexceptions","-mthreads","-fsyntax-only","-m64","--target=x86_64-w64-mingw32","-DUNICODE","-D_UNICODE","-DWIN32","-DMINGW_HAS_SECURE_API","-DQT_NO_DEBUG","-DQT_WIDGETS_LIB","-DQT_GUI_LIB","-DQT_CORE_LIB","-DQT_NEEDS_QMAIN","-DQ_CREATOR_RUN","-DQT_ANNOTATE_FUNCTION(x)=__attribute__((annotate(#x)))","-ID:\\Qt\\Tools\\QtCreator\\share\\qtcreator\\cplusplus\\wrappedMingwHeaders","-ID:\\Qt\\Tools\\QtCreator\\share\\qtcreator\\cplusplus\\wrappedQtHeaders","-ID:\\Qt\\Tools\\QtCreator\\share\\qtcreator\\cplusplus\\wrappedQtHeaders\\QtCore","-ID:\\embeddedprojectgithhub\\TIC_TAK_TOE_PROJECT\\final","-ID:\\Qt\\6.9.1\\mingw_64\\include","-ID:\\Qt\\6.9.1\\mingw_64\\include\\QtWidgets","-ID:\\Qt\\6.9.1\\mingw_64\\include\\QtGui","-ID:\\Qt\\6.9.1\\mingw_64\\include\\QtCore","-ID:\\embeddedprojectgithhub\\TIC_TAK_TOE_PROJECT\\final\\build\\Desktop_Qt_6_9_1_MinGW_64_bit-Release\\release","-ID:\\embeddedprojectgithhub\\TIC_TAK_TOE_PROJECT\\final\\build\\Desktop_Qt_6_9_1_MinGW_64_bit-Release","-ID:\\Qt\\6.9.1\\mingw_64\\mkspecs\\win32-g++","-isystem","D:\\Qt\\Tools\\mingw1310_64\\lib\\gcc\\x86_64-w64-mingw32\\13.1.0\\include\\c++","-isystem","D:\\Qt\\Tools\\mingw1310_64\\lib\\gcc\\x86_64-w64-mingw32\\13.1.0\\include\\c++\\x86_64-w64-mingw32","-isystem","D:\\Qt\\Tools\\mingw1310_64\\lib\\gcc\\x86_64-w64-mingw32\\13.1.0\\include\\c++\\backward","-isystem","D:\\Qt\\Tools\\QtCreator\\bin\\clang\\lib\\clang\\19\\include","-isystem","D:\\Qt\\Tools\\mingw1310_64\\x86_64-w64-mingw32\\include","-fmessage-length=0","-fdiagnostics-show-note-include-stack","-fretain-comments-from-system-headers","-fmacro-backtrace-limit=0","-ferror-limit=1000","-x","c++","D:\\embeddedprojectgithhub\\TIC_TAK_TOE_PROJECT\\final\\Authentication.cpp"],"directory":"D:/embeddedprojectgithhub/TIC_TAK_TOE_PROJECT/final/build/Desktop_Qt_6_9_1_MinGW_64_bit-Release/.qtc_clangd","file":"D:/embeddedprojectgithhub/TIC_TAK_TOE_PROJECT/final/Authentication.cpp"},{"arguments":["clang","-Wno-documentation-unknown-command","-Wno-unknown-warning-option","-Wno-unknown-pragmas","-nostdinc","-nostdinc++","-std=gnu++1z","-Wall","-Wextra","-Wextra","-fexceptions","-mthreads","-fsyntax-only","-m64","--target=x86_64-w64-mingw32","-DUNICODE","-D_UNICODE","-DWIN32","-DMINGW_HAS_SECURE_API","-DQT_NO_DEBUG","-DQT_WIDGETS_LIB","-DQT_GUI_LIB","-DQT_CORE_LIB","-DQT_NEEDS_QMAIN","-DQ_CREATOR_RUN","-DQT_ANNOTATE_FUNCTION(x)=__attribute__((annotate(#x)))","-ID:\\Qt\\Tools\\QtCreator\\share\\qtcreator\\cplusplus\\wrappedMingwHeaders","-ID:\\Qt\\Tools\\QtCreator\\share\\qtcreator\\cplusplus\\wrappedQtHeaders","-ID:\\Qt\\Tools\\QtCreator\\share\\qtcreator\\cplusplus\\wrappedQtHeaders\\QtCore","-ID:\\embeddedprojectgithhub\\TIC_TAK_TOE_PROJECT\\final","-ID:\\Qt\\6.9.1\\mingw_64\\include","-ID:\\Qt\\6.9.1\\mingw_64\\include\\QtWidgets","-ID:\\Qt\\6.9.1\\mingw_64\\include\\QtGui","-ID:\\Qt\\6.9.1\\mingw_64\\include\\QtCore","-ID:\\embeddedprojectgithhub\\TIC_TAK_TOE_PROJECT\\final\\build\\Desktop_Qt_6_9_1_MinGW_64_bit-Release\\release","-ID:\\embeddedprojectgithhub\\TIC_TAK_TOE_PROJECT\\final\\build\\Desktop_Qt_6_9_1_MinGW_64_bit-Release","-ID:\\Qt\\6.9.1\\mingw_64\\mkspecs\\win32-g++","-isystem","D:\\Qt\\Tools\\mingw1310_64\\lib\\gcc\\x86_64-w64-mingw32\\13.1.0\\include\\c++","-isystem","D:\\Qt\\Tools\\mingw1310_64\\lib\\gcc\\x86_64-w64-mingw32\\13.1.0\\include\\c++\\x86_64-w64-mingw32","-isystem","D:\\Qt\\Tools\\mingw1310_64\\lib\\gcc\\x86_64-w64-mingw32\\13.1.0\\include\\c++\\backward","-isystem","D:\\Qt\\Tools\\QtCreator\\bin\\clang\\lib\\clang\\19\\include","-isystem","D:\\Qt\\Tools\\mingw1310_64\\x86_64-w64-mingw32\\include","-fmessage-length=0","-fdiagnostics-show-note-include-stack","-fretain-comments-from-system-headers","-fmacro-backtrace-limit=0","-ferror-limit=1000","-x","c++","D:\\embeddedprojectgithhub\\TIC_TAK_TOE_PROJECT\\final\\Board.cpp"],"directory":"D:/embeddedprojectgithhub/TIC_TAK_TOE_PROJECT/final/build/Desktop_Qt_6_9_1_MinGW_64_bit-Release/.qtc_clangd","file":"D:/embeddedprojectgithhub/TIC_TAK_TOE_PROJECT/final/Board.cpp"},{"arguments":["clang","-Wno-documentation-unknown-command","-Wno-unknown-warning-option","-Wno-unknown-pragmas","-nostdinc","-nostdinc++","-std=gnu++1z","-Wall","-Wextra","-Wextra","-fexceptions","-mthreads","-fsyntax-only","-m64","--target=x86_64-w64-mingw32","-DUNICODE","-D_UNICODE","-DWIN32","-DMINGW_HAS_SECURE_API","-DQT_NO_DEBUG","-DQT_WIDGETS_LIB","-DQT_GUI_LIB","-DQT_CORE_LIB","-DQT_NEEDS_QMAIN","-DQ_CREATOR_RUN","-DQT_ANNOTATE_FUNCTION(x)=__attribute__((annotate(#x)))","-ID:\\Qt\\Tools\\QtCreator\\share\\qtcreator\\cplusplus\\wrappedMingwHeaders","-ID:\\Qt\\Tools\\QtCreator\\share\\qtcreator\\cplusplus\\wrappedQtHeaders","-ID:\\Qt\\Tools\\QtCreator\\share\\qtcreator\\cplusplus\\wrappedQtHeaders\\QtCore","-ID:\\embeddedprojectgithhub\\TIC_TAK_TOE_PROJECT\\final","-ID:\\Qt\\6.9.1\\mingw_64\\include","-ID:\\Qt\\6.9.1\\mingw_64\\include\\QtWidgets","-ID:\\Qt\\6.9.1\\mingw_64\\include\\QtGui","-ID:\\Qt\\6.9.1\\mingw_64\\include\\QtCore","-ID:\\embeddedprojectgithhub\\TIC_TAK_TOE_PROJECT\\final\\build\\Desktop_Qt_6_9_1_MinGW_64_bit-Release\\release","-ID:\\embeddedprojectgithhub\\TIC_TAK_TOE_PROJECT\\final\\build\\Desktop_Qt_6_9_1_MinGW_64_bit-Release","-ID:\\Qt\\6.9.1\\mingw_64\\mkspecs\\win32-g++","-isystem","D:\\Qt\\Tools\\mingw1310_64\\lib\\gcc\\x86_64-w64-mingw32\\13.1.0\\include\\c++","-isystem","D:\\Qt\\Tools\\mingw1310_64\\lib\\gcc\\x86_64-w64-mingw32\\13.1.0\\include\\c++\\x86_64-w64-mingw32","-isystem","D:\\Qt\\Tools\\mingw1310_64\\lib\\gcc\\x86_64-w64-mingw32\\13.1.0\\include\\c++\\backward","-isystem","D:\\Qt\\Tools\\QtCreator\\bin\\clang\\lib\\clang\\19\\include","-isystem","D:\\Qt\\Tools\\mingw1310_64\\x86_64-w64-mingw32\\include","-fmessage-length=0","-fdiagnostics-show-note-include-stack","-fretain-comments-from-system-headers","-fmacro-backtrace-limit=0","-ferror-limit=1000","-x","c++","D:\\embeddedprojectgithhub\\TIC_TAK_TOE_PROJECT\\final\\ai_opponent.cpp"],"directory":"D:/embeddedprojectgithhub/TIC_TAK_TOE_PROJECT/final/build/Desktop_Qt_6_9_1_MinGW_64_bit-Release/.qtc_clangd","file":"D:/embeddedprojectgithhub/TIC_TAK_TOE_PROJECT/final/ai_opponent.cpp"},{"arguments":["clang","-Wno-documentation-unknown-command","-Wno-unknown-warning-option","-Wno-unknown-pragmas","-nostdinc","-nostdinc++","-std=gnu++1z","-Wall","-Wextra","-Wextra","-fexceptions","-mthreads","-fsyntax-only","-m64","--target=x86_64-w64-mingw32","-DUNICODE","-D_UNICODE","-DWIN32","-DMINGW_HAS_SECURE_API","-DQT_NO_DEBUG","-DQT_WIDGETS_LIB","-DQT_GUI_LIB","-DQT_CORE_LIB","-DQT_NEEDS_QMAIN","-DQ_CREATOR_RUN","-DQT_ANNOTATE_FUNCTION(x)=__attribute__((annotate(#x)))","-ID:\\Qt\\Tools\\QtCreator\\share\\qtcreator\\cplusplus\\wrappedMingwHeaders","-ID:\\Qt\\Tools\\QtCreator\\share\\qtcreator\\cplusplus\\wrappedQtHeaders","-ID:\\Qt\\Tools\\QtCreator\\share\\qtcreator\\cplusplus\\wrappedQtHeaders\\QtCore","-ID:\\embeddedprojectgithhub\\TIC_TAK_TOE_PROJECT\\final","-ID:\\Qt\\6.9.1\\mingw_64\\include","-ID:\\Qt\\6.9.1\\mingw_64\\include\\QtWidgets","-ID:\\Qt\\6.9.1\\mingw_64\\include\\QtGui","-ID:\\Qt\\6.9.1\\mingw_64\\include\\QtCore","-ID:\\embeddedprojectgithhub\\TIC_TAK_TOE_PROJECT\\final\\build\\Desktop_Qt_6_9_1_MinGW_64_bit-Release\\release","-ID:\\embeddedprojectgithhub\\TIC_TAK_TOE_PROJECT\\final\\build\\Desktop_Qt_6_9_1_MinGW_64_bit-Release","-ID:\\Qt\\6.9.1\\mingw_64\\mkspecs\\win32-g++","-isystem","D:\\Qt\\Tools\\mingw1310_64\\lib\\gcc\\x86_64-w64-mingw32\\13.1.0\\include\\c++","-isystem","D:\\Qt\\Tools\\mingw1310_64\\lib\\gcc\\x86_64-w64-mingw32\\13.1.0\\include\\c++\\x86_64-w64-mingw32","-isystem","D:\\Qt\\Tools\\mingw1310_64\\lib\\gcc\\x86_64-w64-mingw32\\13.1.0\\include\\c++\\backward","-isystem","D:\\Qt\\Tools\\QtCreator\\bin\\clang\\lib\\clang\\19\\include","-isystem","D:\\Qt\\Tools\\mingw1310_64\\x86_64-w64-mingw32\\include","-fmessage-length=0","-fdiagnostics-show-note-include-stack","-fretain-comments-from-system-headers","-fmacro-backtrace-limit=0","-ferror-limit=1000","-x","c++","D:\\embeddedprojectgithhub\\TIC_TAK_TOE_PROJECT\\final\\codeverification.cpp"],"directory":"D:/embeddedprojectgithhub/TIC_TAK_TOE_PROJECT/final/build/Desktop_Qt_6_9_1_MinGW_64_bit-Release/.qtc_clangd","file":"D:/embeddedprojectgithhub/TIC_TAK_TOE_PROJECT/final/codeverification.cpp"},{"arguments":["clang","-Wno-documentation-unknown-command","-Wno-unknown-warning-option","-Wno-unknown-pragmas","-nostdinc","-nostdinc++","-std=gnu++1z","-Wall","-Wextra","-Wextra","-fexceptions","-mthreads","-fsyntax-only","-m64","--target=x86_64-w64-mingw32","-DUNICODE","-D_UNICODE","-DWIN32","-DMINGW_HAS_SECURE_API","-DQT_NO_DEBUG","-DQT_WIDGETS_LIB","-DQT_GUI_LIB","-DQT_CORE_LIB","-DQT_NEEDS_QMAIN","-DQ_CREATOR_RUN","-DQT_ANNOTATE_FUNCTION(x)=__attribute__((annotate(#x)))","-ID:\\Qt\\Tools\\QtCreator\\share\\qtcreator\\cplusplus\\wrappedMingwHeaders","-ID:\\Qt\\Tools\\QtCreator\\share\\qtcreator\\cplusplus\\wrappedQtHeaders","-ID:\\Qt\\Tools\\QtCreator\\share\\qtcreator\\cplusplus\\wrappedQtHeaders\\QtCore","-ID:\\embeddedprojectgithhub\\TIC_TAK_TOE_PROJECT\\final","-ID:\\Qt\\6.9.1\\mingw_64\\include","-ID:\\Qt\\6.9.1\\mingw_64\\include\\QtWidgets","-ID:\\Qt\\6.9.1\\mingw_64\\include\\QtGui","-ID:\\Qt\\6.9.1\\mingw_64\\include\\QtCore","-ID:\\embeddedprojectgithhub\\TIC_TAK_TOE_PROJECT\\final\\build\\Desktop_Qt_6_9_1_MinGW_64_bit-Release\\release","-ID:\\embeddedprojectgithhub\\TIC_TAK_TOE_PROJECT\\final\\build\\Desktop_Qt_6_9_1_MinGW_64_bit-Release","-ID:\\Qt\\6.9.1\\mingw_64\\mkspecs\\win32-g++","-isystem","D:\\Qt\\Tools\\mingw1310_64\\lib\\gcc\\x86_64-w64-mingw32\\13.1.0\\include\\c++","-isystem","D:\\Qt\\Tools\\mingw1310_64\\lib\\gcc\\x86_64-w64-mingw32\\13.1.0\\include\\c++\\x86_64-w64-mingw32","-isystem","D:\\Qt\\Tools\\mingw1310_64\\lib\\gcc\\x86_64-w64-mingw32\\13.1.0\\include\\c++\\backward","-isystem","D:\\Qt\\Tools\\QtCreator\\bin\\clang\\lib\\clang\\19\\include","-isystem","D:\\Qt\\Tools\\mingw1310_64\\x86_64-w64-mingw32\\include","-fmessage-length=0","-fdiagnostics-show-note-include-stack","-fretain-comments-from-system-headers","-fmacro-backtrace-limit=0","-ferror-limit=1000","-x","c++","D:\\embeddedprojectgithhub\\TIC_TAK_TOE_PROJECT\\final\\game.cpp"],"directory":"D:/embeddedprojectgithhub/TIC_TAK_TOE_PROJECT/final/build/Desktop_Qt_6_9_1_MinGW_64_bit-Release/.qtc_clangd","file":"D:/embeddedprojectgithhub/TIC_TAK_TOE_PROJECT/final/game.cpp"},{"arguments":["clang","-Wno-documentation-unknown-command","-Wno-unknown-warning-option","-Wno-unknown-pragmas","-nostdinc","-nostdinc++","-std=gnu++1z","-Wall","-Wextra","-Wextra","-fexceptions","-mthreads","-fsyntax-only","-m64","--target=x86_64-w64-mingw32","-DUNICODE","-D_UNICODE","-DWIN32","-DMINGW_HAS_SECURE_API","-DQT_NO_DEBUG","-DQT_WIDGETS_LIB","-DQT_GUI_LIB","-DQT_CORE_LIB","-DQT_NEEDS_QMAIN","-DQ_CREATOR_RUN","-DQT_ANNOTATE_FUNCTION(x)=__attribute__((annotate(#x)))","-ID:\\Qt\\Tools\\QtCreator\\share\\qtcreator\\cplusplus\\wrappedMingwHeaders","-ID:\\Qt\\Tools\\QtCreator\\share\\qtcreator\\cplusplus\\wrappedQtHeaders","-ID:\\Qt\\Tools\\QtCreator\\share\\qtcreator\\cplusplus\\wrappedQtHeaders\\QtCore","-ID:\\embeddedprojectgithhub\\TIC_TAK_TOE_PROJECT\\final","-ID:\\Qt\\6.9.1\\mingw_64\\include","-ID:\\Qt\\6.9.1\\mingw_64\\include\\QtWidgets","-ID:\\Qt\\6.9.1\\mingw_64\\include\\QtGui","-ID:\\Qt\\6.9.1\\mingw_64\\include\\QtCore","-ID:\\embeddedprojectgithhub\\TIC_TAK_TOE_PROJECT\\final\\build\\Desktop_Qt_6_9_1_MinGW_64_bit-Release\\release","-ID:\\embeddedprojectgithhub\\TIC_TAK_TOE_PROJECT\\final\\build\\Desktop_Qt_6_9_1_MinGW_64_bit-Release","-ID:\\Qt\\6.9.1\\mingw_64\\mkspecs\\win32-g++","-isystem","D:\\Qt\\Tools\\mingw1310_64\\lib\\gcc\\x86_64-w64-mingw32\\13.1.0\\include\\c++","-isystem","D:\\Qt\\Tools\\mingw1310_64\\lib\\gcc\\x86_64-w64-mingw32\\13.1.0\\include\\c++\\x86_64-w64-mingw32","-isystem","D:\\Qt\\Tools\\mingw1310_64\\lib\\gcc\\x86_64-w64-mingw32\\13.1.0\\include\\c++\\backward","-isystem","D:\\Qt\\Tools\\QtCreator\\bin\\clang\\lib\\clang\\19\\include","-isystem","D:\\Qt\\Tools\\mingw1310_64\\x86_64-w64-mingw32\\include","-fmessage-length=0","-fdiagnostics-show-note-include-stack","-fretain-comments-from-system-headers","-fmacro-backtrace-limit=0","-ferror-limit=1000","-x","c++","D:\\embeddedprojectgithhub\\TIC_TAK_TOE_PROJECT\\final\\gamelogic.cpp"],"directory":"D:/embeddedprojectgithhub/TIC_TAK_TOE_PROJECT/final/build/Desktop_Qt_6_9_1_MinGW_64_bit-Release/.qtc_clangd","file":"D:/embeddedprojectgithhub/TIC_TAK_TOE_PROJECT/final/gamelogic.cpp"},{"arguments":["clang","-Wno-documentation-unknown-command","-Wno-unknown-warning-option","-Wno-unknown-pragmas","-nostdinc","-nostdinc++","-std=gnu++1z","-Wall","-Wextra","-Wextra","-fexceptions","-mthreads","-fsyntax-only","-m64","--target=x86_64-w64-mingw32","-DUNICODE","-D_UNICODE","-DWIN32","-DMINGW_HAS_SECURE_API","-DQT_NO_DEBUG","-DQT_WIDGETS_LIB","-DQT_GUI_LIB","-DQT_CORE_LIB","-DQT_NEEDS_QMAIN","-DQ_CREATOR_RUN","-DQT_ANNOTATE_FUNCTION(x)=__attribute__((annotate(#x)))","-ID:\\Qt\\Tools\\QtCreator\\share\\qtcreator\\cplusplus\\wrappedMingwHeaders","-ID:\\Qt\\Tools\\QtCreator\\share\\qtcreator\\cplusplus\\wrappedQtHeaders","-ID:\\Qt\\Tools\\QtCreator\\share\\qtcreator\\cplusplus\\wrappedQtHeaders\\QtCore","-ID:\\embeddedprojectgithhub\\TIC_TAK_TOE_PROJECT\\final","-ID:\\Qt\\6.9.1\\mingw_64\\include","-ID:\\Qt\\6.9.1\\mingw_64\\include\\QtWidgets","-ID:\\Qt\\6.9.1\\mingw_64\\include\\QtGui","-ID:\\Qt\\6.9.1\\mingw_64\\include\\QtCore","-ID:\\embeddedprojectgithhub\\TIC_TAK_TOE_PROJECT\\final\\build\\Desktop_Qt_6_9_1_MinGW_64_bit-Release\\release","-ID:\\embeddedprojectgithhub\\TIC_TAK_TOE_PROJECT\\final\\build\\Desktop_Qt_6_9_1_MinGW_64_bit-Release","-ID:\\Qt\\6.9.1\\mingw_64\\mkspecs\\win32-g++","-isystem","D:\\Qt\\Tools\\mingw1310_64\\lib\\gcc\\x86_64-w64-mingw32\\13.1.0\\include\\c++","-isystem","D:\\Qt\\Tools\\mingw1310_64\\lib\\gcc\\x86_64-w64-mingw32\\13.1.0\\include\\c++\\x86_64-w64-mingw32","-isystem","D:\\Qt\\Tools\\mingw1310_64\\lib\\gcc\\x86_64-w64-mingw32\\13.1.0\\include\\c++\\backward","-isystem","D:\\Qt\\Tools\\QtCreator\\bin\\clang\\lib\\clang\\19\\include","-isystem","D:\\Qt\\Tools\\mingw1310_64\\x86_64-w64-mingw32\\include","-fmessage-length=0","-fdiagnostics-show-note-include-stack","-fretain-comments-from-system-headers","-fmacro-backtrace-limit=0","-ferror-limit=1000","-x","c++","D:\\embeddedprojectgithhub\\TIC_TAK_TOE_PROJECT\\final\\gamemanager.cpp"],"directory":"D:/embeddedprojectgithhub/TIC_TAK_TOE_PROJECT/final/build/Desktop_Qt_6_9_1_MinGW_64_bit-Release/.qtc_clangd","file":"D:/embeddedprojectgithhub/TIC_TAK_TOE_PROJECT/final/gamemanager.cpp"},{"arguments":["clang","-Wno-documentation-unknown-command","-Wno-unknown-warning-option","-Wno-unknown-pragmas","-nostdinc","-nostdinc++","-std=gnu++1z","-Wall","-Wextra","-Wextra","-fexceptions","-mthreads","-fsyntax-only","-m64","--target=x86_64-w64-mingw32","-DUNICODE","-D_UNICODE","-DWIN32","-DMINGW_HAS_SECURE_API","-DQT_NO_DEBUG","-DQT_WIDGETS_LIB","-DQT_GUI_LIB","-DQT_CORE_LIB","-DQT_NEEDS_QMAIN","-DQ_CREATOR_RUN","-DQT_ANNOTATE_FUNCTION(x)=__attribute__((annotate(#x)))","-ID:\\Qt\\Tools\\QtCreator\\share\\qtcreator\\cplusplus\\wrappedMingwHeaders","-ID:\\Qt\\Tools\\QtCreator\\share\\qtcreator\\cplusplus\\wrappedQtHeaders","-ID:\\Qt\\Tools\\QtCreator\\share\\qtcreator\\cplusplus\\wrappedQtHeaders\\QtCore","-ID:\\embeddedprojectgithhub\\TIC_TAK_TOE_PROJECT\\final","-ID:\\Qt\\6.9.1\\mingw_64\\include","-ID:\\Qt\\6.9.1\\mingw_64\\include\\QtWidgets","-ID:\\Qt\\6.9.1\\mingw_64\\include\\QtGui","-ID:\\Qt\\6.9.1\\mingw_64\\include\\QtCore","-ID:\\embeddedprojectgithhub\\TIC_TAK_TOE_PROJECT\\final\\build\\Desktop_Qt_6_9_1_MinGW_64_bit-Release\\release","-ID:\\embeddedprojectgithhub\\TIC_TAK_TOE_PROJECT\\final\\build\\Desktop_Qt_6_9_1_MinGW_64_bit-Release","-ID:\\Qt\\6.9.1\\mingw_64\\mkspecs\\win32-g++","-isystem","D:\\Qt\\Tools\\mingw1310_64\\lib\\gcc\\x86_64-w64-mingw32\\13.1.0\\include\\c++","-isystem","D:\\Qt\\Tools\\mingw1310_64\\lib\\gcc\\x86_64-w64-mingw32\\13.1.0\\include\\c++\\x86_64-w64-mingw32","-isystem","D:\\Qt\\Tools\\mingw1310_64\\lib\\gcc\\x86_64-w64-mingw32\\13.1.0\\include\\c++\\backward","-isystem","D:\\Qt\\Tools\\QtCreator\\bin\\clang\\lib\\clang\\19\\include","-isystem","D:\\Qt\\Tools\\mingw1310_64\\x86_64-w64-mingw32\\include","-fmessage-length=0","-fdiagnostics-show-note-include-stack","-fretain-comments-from-system-headers","-fmacro-backtrace-limit=0","-ferror-limit=1000","-x","c++","D:\\embeddedprojectgithhub\\TIC_TAK_TOE_PROJECT\\final\\globals.cpp"],"directory":"D:/embeddedprojectgithhub/TIC_TAK_TOE_PROJECT/final/build/Desktop_Qt_6_9_1_MinGW_64_bit-Release/.qtc_clangd","file":"D:/embeddedprojectgithhub/TIC_TAK_TOE_PROJECT/final/globals.cpp"},{"arguments":["clang","-Wno-documentation-unknown-command","-Wno-unknown-warning-option","-Wno-unknown-pragmas","-nostdinc","-nostdinc++","-std=gnu++1z","-Wall","-Wextra","-Wextra","-fexceptions","-mthreads","-fsyntax-only","-m64","--target=x86_64-w64-mingw32","-DUNICODE","-D_UNICODE","-DWIN32","-DMINGW_HAS_SECURE_API","-DQT_NO_DEBUG","-DQT_WIDGETS_LIB","-DQT_GUI_LIB","-DQT_CORE_LIB","-DQT_NEEDS_QMAIN","-DQ_CREATOR_RUN","-DQT_ANNOTATE_FUNCTION(x)=__attribute__((annotate(#x)))","-ID:\\Qt\\Tools\\QtCreator\\share\\qtcreator\\cplusplus\\wrappedMingwHeaders","-ID:\\Qt\\Tools\\QtCreator\\share\\qtcreator\\cplusplus\\wrappedQtHeaders","-ID:\\Qt\\Tools\\QtCreator\\share\\qtcreator\\cplusplus\\wrappedQtHeaders\\QtCore","-ID:\\embeddedprojectgithhub\\TIC_TAK_TOE_PROJECT\\final","-ID:\\Qt\\6.9.1\\mingw_64\\include","-ID:\\Qt\\6.9.1\\mingw_64\\include\\QtWidgets","-ID:\\Qt\\6.9.1\\mingw_64\\include\\QtGui","-ID:\\Qt\\6.9.1\\mingw_64\\include\\QtCore","-ID:\\embeddedprojectgithhub\\TIC_TAK_TOE_PROJECT\\final\\build\\Desktop_Qt_6_9_1_MinGW_64_bit-Release\\release","-ID:\\embeddedprojectgithhub\\TIC_TAK_TOE_PROJECT\\final\\build\\Desktop_Qt_6_9_1_MinGW_64_bit-Release","-ID:\\Qt\\6.9.1\\mingw_64\\mkspecs\\win32-g++","-isystem","D:\\Qt\\Tools\\mingw1310_64\\lib\\gcc\\x86_64-w64-mingw32\\13.1.0\\include\\c++","-isystem","D:\\Qt\\Tools\\mingw1310_64\\lib\\gcc\\x86_64-w64-mingw32\\13.1.0\\include\\c++\\x86_64-w64-mingw32","-isystem","D:\\Qt\\Tools\\mingw1310_64\\lib\\gcc\\x86_64-w64-mingw32\\13.1.0\\include\\c++\\backward","-isystem","D:\\Qt\\Tools\\QtCreator\\bin\\clang\\lib\\clang\\19\\include","-isystem","D:\\Qt\\Tools\\mingw1310_64\\x86_64-w64-mingw32\\include","-fmessage-length=0","-fdiagnostics-show-note-include-stack","-fretain-comments-from-system-headers","-fmacro-backtrace-limit=0","-ferror-limit=1000","-x","c++","D:\\embeddedprojectgithhub\\TIC_TAK_TOE_PROJECT\\final\\historymanager.cpp"],"directory":"D:/embeddedprojectgithhub/TIC_TAK_TOE_PROJECT/final/build/Desktop_Qt_6_9_1_MinGW_64_bit-Release/.qtc_clangd","file":"D:/embeddedprojectgithhub/TIC_TAK_TOE_PROJECT/final/historymanager.cpp"},{"arguments":["clang","-Wno-documentation-unknown-command","-Wno-unknown-warning-option","-Wno-unknown-pragmas","-nostdinc","-nostdinc++","-std=gnu++1z","-Wall","-Wextra","-Wextra","-fexceptions","-mthreads","-fsyntax-only","-m64","--target=x86_64-w64-mingw32","-DUNICODE","-D_UNICODE","-DWIN32","-DMINGW_HAS_SECURE_API","-DQT_NO_DEBUG","-DQT_WIDGETS_LIB","-DQT_GUI_LIB","-DQT_CORE_LIB","-DQT_NEEDS_QMAIN","-DQ_CREATOR_RUN","-DQT_ANNOTATE_FUNCTION(x)=__attribute__((annotate(#x)))","-ID:\\Qt\\Tools\\QtCreator\\share\\qtcreator\\cplusplus\\wrappedMingwHeaders","-ID:\\Qt\\Tools\\QtCreator\\share\\qtcreator\\cplusplus\\wrappedQtHeaders","-ID:\\Qt\\Tools\\QtCreator\\share\\qtcreator\\cplusplus\\wrappedQtHeaders\\QtCore","-ID:\\embeddedprojectgithhub\\TIC_TAK_TOE_PROJECT\\final","-ID:\\Qt\\6.9.1\\mingw_64\\include","-ID:\\Qt\\6.9.1\\mingw_64\\include\\QtWidgets","-ID:\\Qt\\6.9.1\\mingw_64\\include\\QtGui","-ID:\\Qt\\6.9.1\\mingw_64\\include\\QtCore","-ID:\\embeddedprojectgithhub\\TIC_TAK_TOE_PROJECT\\final\\build\\Desktop_Qt_6_9_1_MinGW_64_bit-Release\\release","-ID:\\embeddedprojectgithhub\\TIC_TAK_TOE_PROJECT\\final\\build\\Desktop_Qt_6_9_1_MinGW_64_bit-Release","-ID:\\Qt\\6.9.1\\mingw_64\\mkspecs\\win32-g++","-isystem","D:\\Qt\\Tools\\mingw1310_64\\lib\\gcc\\x86_64-w64-mingw32\\13.1.0\\include\\c++","-isystem","D:\\Qt\\Tools\\mingw1310_64\\lib\\gcc\\x86_64-w64-mingw32\\13.1.0\\include\\c++\\x86_64-w64-mingw32","-isystem","D:\\Qt\\Tools\\mingw1310_64\\lib\\gcc\\x86_64-w64-mingw32\\13.1.0\\include\\c++\\backward","-isystem","D:\\Qt\\Tools\\QtCreator\\bin\\clang\\lib\\clang\\19\\include","-isystem","D:\\Qt\\Tools\\mingw1310_64\\x86_64-w64-mingw32\\include","-fmessage-length=0","-fdiagnostics-show-note-include-stack","-fretain-comments-from-system-headers","-fmacro-backtrace-limit=0","-ferror-limit=1000","-x","c++","D:\\embeddedprojectgithhub\\TIC_TAK_TOE_PROJECT\\final\\home.cpp"],"directory":"D:/embeddedprojectgithhub/TIC_TAK_TOE_PROJECT/final/build/Desktop_Qt_6_9_1_MinGW_64_bit-Release/.qtc_clangd","file":"D:/embeddedprojectgithhub/TIC_TAK_TOE_PROJECT/final/home.cpp"},{"arguments":["clang","-Wno-documentation-unknown-command","-Wno-unknown-warning-option","-Wno-unknown-pragmas","-nostdinc","-nostdinc++","-std=gnu++1z","-Wall","-Wextra","-Wextra","-fexceptions","-mthreads","-fsyntax-only","-m64","--target=x86_64-w64-mingw32","-DUNICODE","-D_UNICODE","-DWIN32","-DMINGW_HAS_SECURE_API","-DQT_NO_DEBUG","-DQT_WIDGETS_LIB","-DQT_GUI_LIB","-DQT_CORE_LIB","-DQT_NEEDS_QMAIN","-DQ_CREATOR_RUN","-DQT_ANNOTATE_FUNCTION(x)=__attribute__((annotate(#x)))","-ID:\\Qt\\Tools\\QtCreator\\share\\qtcreator\\cplusplus\\wrappedMingwHeaders","-ID:\\Qt\\Tools\\QtCreator\\share\\qtcreator\\cplusplus\\wrappedQtHeaders","-ID:\\Qt\\Tools\\QtCreator\\share\\qtcreator\\cplusplus\\wrappedQtHeaders\\QtCore","-ID:\\embeddedprojectgithhub\\TIC_TAK_TOE_PROJECT\\final","-ID:\\Qt\\6.9.1\\mingw_64\\include","-ID:\\Qt\\6.9.1\\mingw_64\\include\\QtWidgets","-ID:\\Qt\\6.9.1\\mingw_64\\include\\QtGui","-ID:\\Qt\\6.9.1\\mingw_64\\include\\QtCore","-ID:\\embeddedprojectgithhub\\TIC_TAK_TOE_PROJECT\\final\\build\\Desktop_Qt_6_9_1_MinGW_64_bit-Release\\release","-ID:\\embeddedprojectgithhub\\TIC_TAK_TOE_PROJECT\\final\\build\\Desktop_Qt_6_9_1_MinGW_64_bit-Release","-ID:\\Qt\\6.9.1\\mingw_64\\mkspecs\\win32-g++","-isystem","D:\\Qt\\Tools\\mingw1310_64\\lib\\gcc\\x86_64-w64-mingw32\\13.1.0\\include\\c++","-isystem","D:\\Qt\\Tools\\mingw1310_64\\lib\\gcc\\x86_64-w64-mingw32\\13.1.0\\include\\c++\\x86_64-w64-mingw32","-isystem","D:\\Qt\\Tools\\mingw1310_64\\lib\\gcc\\x86_64-w64-mingw32\\13.1.0\\include\\c++\\backward","-isystem","D:\\Qt\\Tools\\QtCreator\\bin\\clang\\lib\\clang\\19\\include","-isystem","D:\\Qt\\Tools\\mingw1310_64\\x86_64-w64-mingw32\\include","-fmessage-length=0","-fdiagnostics-show-note-include-stack","-fretain-comments-from-system-headers","-fmacro-backtrace-limit=0","-ferror-limit=1000","-x","c++","D:\\embeddedprojectgithhub\\TIC_TAK_TOE_PROJECT\\final\\login.cpp"],"directory":"D:/embeddedprojectgithhub/TIC_TAK_TOE_PROJECT/final/build/Desktop_Qt_6_9_1_MinGW_64_bit-Release/.qtc_clangd","file":"D:/embeddedprojectgithhub/TIC_TAK_TOE_PROJECT/final/login.cpp"},{"arguments":["clang","-Wno-documentation-unknown-command","-Wno-unknown-warning-option","-Wno-unknown-pragmas","-nostdinc","-nostdinc++","-std=gnu++1z","-Wall","-Wextra","-Wextra","-fexceptions","-mthreads","-fsyntax-only","-m64","--target=x86_64-w64-mingw32","-DUNICODE","-D_UNICODE","-DWIN32","-DMINGW_HAS_SECURE_API","-DQT_NO_DEBUG","-DQT_WIDGETS_LIB","-DQT_GUI_LIB","-DQT_CORE_LIB","-DQT_NEEDS_QMAIN","-DQ_CREATOR_RUN","-DQT_ANNOTATE_FUNCTION(x)=__attribute__((annotate(#x)))","-ID:\\Qt\\Tools\\QtCreator\\share\\qtcreator\\cplusplus\\wrappedMingwHeaders","-ID:\\Qt\\Tools\\QtCreator\\share\\qtcreator\\cplusplus\\wrappedQtHeaders","-ID:\\Qt\\Tools\\QtCreator\\share\\qtcreator\\cplusplus\\wrappedQtHeaders\\QtCore","-ID:\\embeddedprojectgithhub\\TIC_TAK_TOE_PROJECT\\final","-ID:\\Qt\\6.9.1\\mingw_64\\include","-ID:\\Qt\\6.9.1\\mingw_64\\include\\QtWidgets","-ID:\\Qt\\6.9.1\\mingw_64\\include\\QtGui","-ID:\\Qt\\6.9.1\\mingw_64\\include\\QtCore","-ID:\\embeddedprojectgithhub\\TIC_TAK_TOE_PROJECT\\final\\build\\Desktop_Qt_6_9_1_MinGW_64_bit-Release\\release","-ID:\\embeddedprojectgithhub\\TIC_TAK_TOE_PROJECT\\final\\build\\Desktop_Qt_6_9_1_MinGW_64_bit-Release","-ID:\\Qt\\6.9.1\\mingw_64\\mkspecs\\win32-g++","-isystem","D:\\Qt\\Tools\\mingw1310_64\\lib\\gcc\\x86_64-w64-mingw32\\13.1.0\\include\\c++","-isystem","D:\\Qt\\Tools\\mingw1310_64\\lib\\gcc\\x86_64-w64-mingw32\\13.1.0\\include\\c++\\x86_64-w64-mingw32","-isystem","D:\\Qt\\Tools\\mingw1310_64\\lib\\gcc\\x86_64-w64-mingw32\\13.1.0\\include\\c++\\backward","-isystem","D:\\Qt\\Tools\\QtCreator\\bin\\clang\\lib\\clang\\19\\include","-isystem","D:\\Qt\\Tools\\mingw1310_64\\x86_64-w64-mingw32\\include","-fmessage-length=0","-fdiagnostics-show-note-include-stack","-fretain-comments-from-system-headers","-fmacro-backtrace-limit=0","-ferror-limit=1000","-x","c++","D:\\embeddedprojectgithhub\\TIC_TAK_TOE_PROJECT\\final\\main.cpp"],"directory":"D:/embeddedprojectgithhub/TIC_TAK_TOE_PROJECT/final/build/Desktop_Qt_6_9_1_MinGW_64_bit-Release/.qtc_clangd","file":"D:/embeddedprojectgithhub/TIC_TAK_TOE_PROJECT/final/main.cpp"},{"arguments":["clang","-Wno-documentation-unknown-command","-Wno-unknown-warning-option","-Wno-unknown-pragmas","-nostdinc","-nostdinc++","-std=gnu++1z","-Wall","-Wextra","-Wextra","-fexceptions","-mthreads","-fsyntax-only","-m64","--target=x86_64-w64-mingw32","-DUNICODE","-D_UNICODE","-DWIN32","-DMINGW_HAS_SECURE_API","-DQT_NO_DEBUG","-DQT_WIDGETS_LIB","-DQT_GUI_LIB","-DQT_CORE_LIB","-DQT_NEEDS_QMAIN","-DQ_CREATOR_RUN","-DQT_ANNOTATE_FUNCTION(x)=__attribute__((annotate(#x)))","-ID:\\Qt\\Tools\\QtCreator\\share\\qtcreator\\cplusplus\\wrappedMingwHeaders","-ID:\\Qt\\Tools\\QtCreator\\share\\qtcreator\\cplusplus\\wrappedQtHeaders","-ID:\\Qt\\Tools\\QtCreator\\share\\qtcreator\\cplusplus\\wrappedQtHeaders\\QtCore","-ID:\\embeddedprojectgithhub\\TIC_TAK_TOE_PROJECT\\final","-ID:\\Qt\\6.9.1\\mingw_64\\include","-ID:\\Qt\\6.9.1\\mingw_64\\include\\QtWidgets","-ID:\\Qt\\6.9.1\\mingw_64\\include\\QtGui","-ID:\\Qt\\6.9.1\\mingw_64\\include\\QtCore","-ID:\\embeddedprojectgithhub\\TIC_TAK_TOE_PROJECT\\final\\build\\Desktop_Qt_6_9_1_MinGW_64_bit-Release\\release","-ID:\\embeddedprojectgithhub\\TIC_TAK_TOE_PROJECT\\final\\build\\Desktop_Qt_6_9_1_MinGW_64_bit-Release","-ID:\\Qt\\6.9.1\\mingw_64\\mkspecs\\win32-g++","-isystem","D:\\Qt\\Tools\\mingw1310_64\\lib\\gcc\\x86_64-w64-mingw32\\13.1.0\\include\\c++","-isystem","D:\\Qt\\Tools\\mingw1310_64\\lib\\gcc\\x86_64-w64-mingw32\\13.1.0\\include\\c++\\x86_64-w64-mingw32","-isystem","D:\\Qt\\Tools\\mingw1310_64\\lib\\gcc\\x86_64-w64-mingw32\\13.1.0\\include\\c++\\backward","-isystem","D:\\Qt\\Tools\\QtCreator\\bin\\clang\\lib\\clang\\19\\include","-isystem","D:\\Qt\\Tools\\mingw1310_64\\x86_64-w64-mingw32\\include","-fmessage-length=0","-fdiagnostics-show-note-include-stack","-fretain-comments-from-system-headers","-fmacro-backtrace-limit=0","-ferror-limit=1000","-x","c++","D:\\embeddedprojectgithhub\\TIC_TAK_TOE_PROJECT\\final\\mainwindow.cpp"],"directory":"D:/embeddedprojectgithhub/TIC_TAK_TOE_PROJECT/final/build/Desktop_Qt_6_9_1_MinGW_64_bit-Release/.qtc_clangd","file":"D:/embeddedprojectgithhub/TIC_TAK_TOE_PROJECT/final/mainwindow.cpp"},{"arguments":["clang","-Wno-documentation-unknown-command","-Wno-unknown-warning-option","-Wno-unknown-pragmas","-nostdinc","-nostdinc++","-std=gnu++1z","-Wall","-Wextra","-Wextra","-fexceptions","-mthreads","-fsyntax-only","-m64","--target=x86_64-w64-mingw32","-DUNICODE","-D_UNICODE","-DWIN32","-DMINGW_HAS_SECURE_API","-DQT_NO_DEBUG","-DQT_WIDGETS_LIB","-DQT_GUI_LIB","-DQT_CORE_LIB","-DQT_NEEDS_QMAIN","-DQ_CREATOR_RUN","-DQT_ANNOTATE_FUNCTION(x)=__attribute__((annotate(#x)))","-ID:\\Qt\\Tools\\QtCreator\\share\\qtcreator\\cplusplus\\wrappedMingwHeaders","-ID:\\Qt\\Tools\\QtCreator\\share\\qtcreator\\cplusplus\\wrappedQtHeaders","-ID:\\Qt\\Tools\\QtCreator\\share\\qtcreator\\cplusplus\\wrappedQtHeaders\\QtCore","-ID:\\embeddedprojectgithhub\\TIC_TAK_TOE_PROJECT\\final","-ID:\\Qt\\6.9.1\\mingw_64\\include","-ID:\\Qt\\6.9.1\\mingw_64\\include\\QtWidgets","-ID:\\Qt\\6.9.1\\mingw_64\\include\\QtGui","-ID:\\Qt\\6.9.1\\mingw_64\\include\\QtCore","-ID:\\embeddedprojectgithhub\\TIC_TAK_TOE_PROJECT\\final\\build\\Desktop_Qt_6_9_1_MinGW_64_bit-Release\\release","-ID:\\embeddedprojectgithhub\\TIC_TAK_TOE_PROJECT\\final\\build\\Desktop_Qt_6_9_1_MinGW_64_bit-Release","-ID:\\Qt\\6.9.1\\mingw_64\\mkspecs\\win32-g++","-isystem","D:\\Qt\\Tools\\mingw1310_64\\lib\\gcc\\x86_64-w64-mingw32\\13.1.0\\include\\c++","-isystem","D:\\Qt\\Tools\\mingw1310_64\\lib\\gcc\\x86_64-w64-mingw32\\13.1.0\\include\\c++\\x86_64-w64-mingw32","-isystem","D:\\Qt\\Tools\\mingw1310_64\\lib\\gcc\\x86_64-w64-mingw32\\13.1.0\\include\\c++\\backward","-isystem","D:\\Qt\\Tools\\QtCreator\\bin\\clang\\lib\\clang\\19\\include","-isystem","D:\\Qt\\Tools\\mingw1310_64\\x86_64-w64-mingw32\\include","-fmessage-length=0","-fdiagnostics-show-note-include-stack","-fretain-comments-from-system-headers","-fmacro-backtrace-limit=0","-ferror-limit=1000","-x","c++","D:\\embeddedprojectgithhub\\TIC_TAK_TOE_PROJECT\\final\\playboard.cpp"],"directory":"D:/embeddedprojectgithhub/TIC_TAK_TOE_PROJECT/final/build/Desktop_Qt_6_9_1_MinGW_64_bit-Release/.qtc_clangd","file":"D:/embeddedprojectgithhub/TIC_TAK_TOE_PROJECT/final/playboard.cpp"},{"arguments":["clang","-Wno-documentation-unknown-command","-Wno-unknown-warning-option","-Wno-unknown-pragmas","-nostdinc","-nostdinc++","-std=gnu++1z","-Wall","-Wextra","-Wextra","-fexceptions","-mthreads","-fsyntax-only","-m64","--target=x86_64-w64-mingw32","-DUNICODE","-D_UNICODE","-DWIN32","-DMINGW_HAS_SECURE_API","-DQT_NO_DEBUG","-DQT_WIDGETS_LIB","-DQT_GUI_LIB","-DQT_CORE_LIB","-DQT_NEEDS_QMAIN","-DQ_CREATOR_RUN","-DQT_ANNOTATE_FUNCTION(x)=__attribute__((annotate(#x)))","-ID:\\Qt\\Tools\\QtCreator\\share\\qtcreator\\cplusplus\\wrappedMingwHeaders","-ID:\\Qt\\Tools\\QtCreator\\share\\qtcreator\\cplusplus\\wrappedQtHeaders","-ID:\\Qt\\Tools\\QtCreator\\share\\qtcreator\\cplusplus\\wrappedQtHeaders\\QtCore","-ID:\\embeddedprojectgithhub\\TIC_TAK_TOE_PROJECT\\final","-ID:\\Qt\\6.9.1\\mingw_64\\include","-ID:\\Qt\\6.9.1\\mingw_64\\include\\QtWidgets","-ID:\\Qt\\6.9.1\\mingw_64\\include\\QtGui","-ID:\\Qt\\6.9.1\\mingw_64\\include\\QtCore","-ID:\\embeddedprojectgithhub\\TIC_TAK_TOE_PROJECT\\final\\build\\Desktop_Qt_6_9_1_MinGW_64_bit-Release\\release","-ID:\\embeddedprojectgithhub\\TIC_TAK_TOE_PROJECT\\final\\build\\Desktop_Qt_6_9_1_MinGW_64_bit-Release","-ID:\\Qt\\6.9.1\\mingw_64\\mkspecs\\win32-g++","-isystem","D:\\Qt\\Tools\\mingw1310_64\\lib\\gcc\\x86_64-w64-mingw32\\13.1.0\\include\\c++","-isystem","D:\\Qt\\Tools\\mingw1310_64\\lib\\gcc\\x86_64-w64-mingw32\\13.1.0\\include\\c++\\x86_64-w64-mingw32","-isystem","D:\\Qt\\Tools\\mingw1310_64\\lib\\gcc\\x86_64-w64-mingw32\\13.1.0\\include\\c++\\backward","-isystem","D:\\Qt\\Tools\\QtCreator\\bin\\clang\\lib\\clang\\19\\include","-isystem","D:\\Qt\\Tools\\mingw1310_64\\x86_64-w64-mingw32\\include","-fmessage-length=0","-fdiagnostics-show-note-include-stack","-fretain-comments-from-system-headers","-fmacro-backtrace-limit=0","-ferror-limit=1000","-x","c++","D:\\embeddedprojectgithhub\\TIC_TAK_TOE_PROJECT\\final\\playermanager.cpp"],"directory":"D:/embeddedprojectgithhub/TIC_TAK_TOE_PROJECT/final/build/Desktop_Qt_6_9_1_MinGW_64_bit-Release/.qtc_clangd","file":"D:/embeddedprojectgithhub/TIC_TAK_TOE_PROJECT/final/playermanager.cpp"},{"arguments":["clang","-Wno-documentation-unknown-command","-Wno-unknown-warning-option","-Wno-unknown-pragmas","-nostdinc","-nostdinc++","-std=gnu++1z","-Wall","-Wextra","-Wextra","-fexceptions","-mthreads","-fsyntax-only","-m64","--target=x86_64-w64-mingw32","-DUNICODE","-D_UNICODE","-DWIN32","-DMINGW_HAS_SECURE_API","-DQT_NO_DEBUG","-DQT_WIDGETS_LIB","-DQT_GUI_LIB","-DQT_CORE_LIB","-DQT_NEEDS_QMAIN","-DQ_CREATOR_RUN","-DQT_ANNOTATE_FUNCTION(x)=__attribute__((annotate(#x)))","-ID:\\Qt\\Tools\\QtCreator\\share\\qtcreator\\cplusplus\\wrappedMingwHeaders","-ID:\\Qt\\Tools\\QtCreator\\share\\qtcreator\\cplusplus\\wrappedQtHeaders","-ID:\\Qt\\Tools\\QtCreator\\share\\qtcreator\\cplusplus\\wrappedQtHeaders\\QtCore","-ID:\\embeddedprojectgithhub\\TIC_TAK_TOE_PROJECT\\final","-ID:\\Qt\\6.9.1\\mingw_64\\include","-ID:\\Qt\\6.9.1\\mingw_64\\include\\QtWidgets","-ID:\\Qt\\6.9.1\\mingw_64\\include\\QtGui","-ID:\\Qt\\6.9.1\\mingw_64\\include\\QtCore","-ID:\\embeddedprojectgithhub\\TIC_TAK_TOE_PROJECT\\final\\build\\Desktop_Qt_6_9_1_MinGW_64_bit-Release\\release","-ID:\\embeddedprojectgithhub\\TIC_TAK_TOE_PROJECT\\final\\build\\Desktop_Qt_6_9_1_MinGW_64_bit-Release","-ID:\\Qt\\6.9.1\\mingw_64\\mkspecs\\win32-g++","-isystem","D:\\Qt\\Tools\\mingw1310_64\\lib\\gcc\\x86_64-w64-mingw32\\13.1.0\\include\\c++","-isystem","D:\\Qt\\Tools\\mingw1310_64\\lib\\gcc\\x86_64-w64-mingw32\\13.1.0\\include\\c++\\x86_64-w64-mingw32","-isystem","D:\\Qt\\Tools\\mingw1310_64\\lib\\gcc\\x86_64-w64-mingw32\\13.1.0\\include\\c++\\backward","-isystem","D:\\Qt\\Tools\\QtCreator\\bin\\clang\\lib\\clang\\19\\include","-isystem","D:\\Qt\\Tools\\mingw1310_64\\x86_64-w64-mingw32\\include","-fmessage-length=0","-fdiagnostics-show-note-include-stack","-fretain-comments-from-system-headers","-fmacro-backtrace-limit=0","-ferror-limit=1000","-x","c++","D:\\embeddedprojectgithhub\\TIC_TAK_TOE_PROJECT\\final\\replayboard.cpp"],"directory":"D:/embeddedprojectgithhub/TIC_TAK_TOE_PROJECT/final/build/Desktop_Qt_6_9_1_MinGW_64_bit-Release/.qtc_clangd","file":"D:/embeddedprojectgithhub/TIC_TAK_TOE_PROJECT/final/replayboard.cpp"},{"arguments":["clang","-Wno-documentation-unknown-command","-Wno-unknown-warning-option","-Wno-unknown-pragmas","-nostdinc","-nostdinc++","-std=gnu++1z","-Wall","-Wextra","-Wextra","-fexceptions","-mthreads","-fsyntax-only","-m64","--target=x86_64-w64-mingw32","-DUNICODE","-D_UNICODE","-DWIN32","-DMINGW_HAS_SECURE_API","-DQT_NO_DEBUG","-DQT_WIDGETS_LIB","-DQT_GUI_LIB","-DQT_CORE_LIB","-DQT_NEEDS_QMAIN","-DQ_CREATOR_RUN","-DQT_ANNOTATE_FUNCTION(x)=__attribute__((annotate(#x)))","-ID:\\Qt\\Tools\\QtCreator\\share\\qtcreator\\cplusplus\\wrappedMingwHeaders","-ID:\\Qt\\Tools\\QtCreator\\share\\qtcreator\\cplusplus\\wrappedQtHeaders","-ID:\\Qt\\Tools\\QtCreator\\share\\qtcreator\\cplusplus\\wrappedQtHeaders\\QtCore","-ID:\\embeddedprojectgithhub\\TIC_TAK_TOE_PROJECT\\final","-ID:\\Qt\\6.9.1\\mingw_64\\include","-ID:\\Qt\\6.9.1\\mingw_64\\include\\QtWidgets","-ID:\\Qt\\6.9.1\\mingw_64\\include\\QtGui","-ID:\\Qt\\6.9.1\\mingw_64\\include\\QtCore","-ID:\\embeddedprojectgithhub\\TIC_TAK_TOE_PROJECT\\final\\build\\Desktop_Qt_6_9_1_MinGW_64_bit-Release\\release","-ID:\\embeddedprojectgithhub\\TIC_TAK_TOE_PROJECT\\final\\build\\Desktop_Qt_6_9_1_MinGW_64_bit-Release","-ID:\\Qt\\6.9.1\\mingw_64\\mkspecs\\win32-g++","-isystem","D:\\Qt\\Tools\\mingw1310_64\\lib\\gcc\\x86_64-w64-mingw32\\13.1.0\\include\\c++","-isystem","D:\\Qt\\Tools\\mingw1310_64\\lib\\gcc\\x86_64-w64-mingw32\\13.1.0\\include\\c++\\x86_64-w64-mingw32","-isystem","D:\\Qt\\Tools\\mingw1310_64\\lib\\gcc\\x86_64-w64-mingw32\\13.1.0\\include\\c++\\backward","-isystem","D:\\Qt\\Tools\\QtCreator\\bin\\clang\\lib\\clang\\19\\include","-isystem","D:\\Qt\\Tools\\mingw1310_64\\x86_64-w64-mingw32\\include","-fmessage-length=0","-fdiagnostics-show-note-include-stack","-fretain-comments-from-system-headers","-fmacro-backtrace-limit=0","-ferror-limit=1000","-x","c++","D:\\embeddedprojectgithhub\\TIC_TAK_TOE_PROJECT\\final\\sessiontimer.cpp"],"directory":"D:/embeddedprojectgithhub/TIC_TAK_TOE_PROJECT/final/build/Desktop_Qt_6_9_1_MinGW_64_bit-Release/.qtc_clangd","file":"D:/embeddedprojectgithhub/TIC_TAK_TOE_PROJECT/final/sessiontimer.cpp"},{"arguments":["clang","-Wno-documentation-unknown-command","-Wno-unknown-warning-option","-Wno-unknown-pragmas","-nostdinc","-nostdinc++","-std=gnu++1z","-Wall","-Wextra","-Wextra","-fexceptions","-mthreads","-fsyntax-only","-m64","--target=x86_64-w64-mingw32","-DUNICODE","-D_UNICODE","-DWIN32","-DMINGW_HAS_SECURE_API","-DQT_NO_DEBUG","-DQT_WIDGETS_LIB","-DQT_GUI_LIB","-DQT_CORE_LIB","-DQT_NEEDS_QMAIN","-DQ_CREATOR_RUN","-DQT_ANNOTATE_FUNCTION(x)=__attribute__((annotate(#x)))","-ID:\\Qt\\Tools\\QtCreator\\share\\qtcreator\\cplusplus\\wrappedMingwHeaders","-ID:\\Qt\\Tools\\QtCreator\\share\\qtcreator\\cplusplus\\wrappedQtHeaders","-ID:\\Qt\\Tools\\QtCreator\\share\\qtcreator\\cplusplus\\wrappedQtHeaders\\QtCore","-ID:\\embeddedprojectgithhub\\TIC_TAK_TOE_PROJECT\\final","-ID:\\Qt\\6.9.1\\mingw_64\\include","-ID:\\Qt\\6.9.1\\mingw_64\\include\\QtWidgets","-ID:\\Qt\\6.9.1\\mingw_64\\include\\QtGui","-ID:\\Qt\\6.9.1\\mingw_64\\include\\QtCore","-ID:\\embeddedprojectgithhub\\TIC_TAK_TOE_PROJECT\\final\\build\\Desktop_Qt_6_9_1_MinGW_64_bit-Release\\release","-ID:\\embeddedprojectgithhub\\TIC_TAK_TOE_PROJECT\\final\\build\\Desktop_Qt_6_9_1_MinGW_64_bit-Release","-ID:\\Qt\\6.9.1\\mingw_64\\mkspecs\\win32-g++","-isystem","D:\\Qt\\Tools\\mingw1310_64\\lib\\gcc\\x86_64-w64-mingw32\\13.1.0\\include\\c++","-isystem","D:\\Qt\\Tools\\mingw1310_64\\lib\\gcc\\x86_64-w64-mingw32\\13.1.0\\include\\c++\\x86_64-w64-mingw32","-isystem","D:\\Qt\\Tools\\mingw1310_64\\lib\\gcc\\x86_64-w64-mingw32\\13.1.0\\include\\c++\\backward","-isystem","D:\\Qt\\Tools\\QtCreator\\bin\\clang\\lib\\clang\\19\\include","-isystem","D:\\Qt\\Tools\\mingw1310_64\\x86_64-w64-mingw32\\include","-fmessage-length=0","-fdiagnostics-show-note-include-stack","-fretain-comments-from-system-headers","-fmacro-backtrace-limit=0","-ferror-limit=1000","-x","c++-header","D:\\embeddedprojectgithhub\\TIC_TAK_TOE_PROJECT\\final\\json.hpp"],"directory":"D:/embeddedprojectgithhub/TIC_TAK_TOE_PROJECT/final/build/Desktop_Qt_6_9_1_MinGW_64_bit-Release/.qtc_clangd","file":"D:/embeddedprojectgithhub/TIC_TAK_TOE_PROJECT/final/json.hpp"},{"arguments":["clang","-Wno-documentation-unknown-command","-Wno-unknown-warning-option","-Wno-unknown-pragmas","-nostdinc","-nostdinc++","-std=gnu++1z","-Wall","-Wextra","-Wextra","-fexceptions","-mthreads","-fsyntax-only","-m64","--target=x86_64-w64-mingw32","-DUNICODE","-D_UNICODE","-DWIN32","-DMINGW_HAS_SECURE_API","-DQT_NO_DEBUG","-DQT_WIDGETS_LIB","-DQT_GUI_LIB","-DQT_CORE_LIB","-DQT_NEEDS_QMAIN","-DQ_CREATOR_RUN","-DQT_ANNOTATE_FUNCTION(x)=__attribute__((annotate(#x)))","-ID:\\Qt\\Tools\\QtCreator\\share\\qtcreator\\cplusplus\\wrappedMingwHeaders","-ID:\\Qt\\Tools\\QtCreator\\share\\qtcreator\\cplusplus\\wrappedQtHeaders","-ID:\\Qt\\Tools\\QtCreator\\share\\qtcreator\\cplusplus\\wrappedQtHeaders\\QtCore","-ID:\\embeddedprojectgithhub\\TIC_TAK_TOE_PROJECT\\final","-ID:\\Qt\\6.9.1\\mingw_64\\include","-ID:\\Qt\\6.9.1\\mingw_64\\include\\QtWidgets","-ID:\\Qt\\6.9.1\\mingw_64\\include\\QtGui","-ID:\\Qt\\6.9.1\\mingw_64\\include\\QtCore","-ID:\\embeddedprojectgithhub\\TIC_TAK_TOE_PROJECT\\final\\build\\Desktop_Qt_6_9_1_MinGW_64_bit-Release\\release","-ID:\\embeddedprojectgithhub\\TIC_TAK_TOE_PROJECT\\final\\build\\Desktop_Qt_6_9_1_MinGW_64_bit-Release","-ID:\\Qt\\6.9.1\\mingw_64\\mkspecs\\win32-g++","-isystem","D:\\Qt\\Tools\\mingw1310_64\\lib\\gcc\\x86_64-w64-mingw32\\13.1.0\\include\\c++","-isystem","D:\\Qt\\Tools\\mingw1310_64\\lib\\gcc\\x86_64-w64-mingw32\\13.1.0\\include\\c++\\x86_64-w64-mingw32","-isystem","D:\\Qt\\Tools\\mingw1310_64\\lib\\gcc\\x86_64-w64-mingw32\\13.1.0\\include\\c++\\backward","-isystem","D:\\Qt\\Tools\\QtCreator\\bin\\clang\\lib\\clang\\19\\include","-isystem","D:\\Qt\\Tools\\mingw1310_64\\x86_64-w64-mingw32\\include","-fmessage-length=0","-fdiagnostics-show-note-include-stack","-fretain-comments-from-system-headers","-fmacro-backtrace-limit=0","-ferror-limit=1000","-x","c++-header","D:\\embeddedprojectgithhub\\TIC_TAK_TOE_PROJECT\\final\\Authentication.h"],"directory":"D:/embeddedprojectgithhub/TIC_TAK_TOE_PROJECT/final/build/Desktop_Qt_6_9_1_MinGW_64_bit-Release/.qtc_clangd","file":"D:/embeddedprojectgithhub/TIC_TAK_TOE_PROJECT/final/Authentication.h"},{"arguments":["clang","-Wno-documentation-unknown-command","-Wno-unknown-warning-option","-Wno-unknown-pragmas","-nostdinc","-nostdinc++","-std=gnu++1z","-Wall","-Wextra","-Wextra","-fexceptions","-mthreads","-fsyntax-only","-m64","--target=x86_64-w64-mingw32","-DUNICODE","-D_UNICODE","-DWIN32","-DMINGW_HAS_SECURE_API","-DQT_NO_DEBUG","-DQT_WIDGETS_LIB","-DQT_GUI_LIB","-DQT_CORE_LIB","-DQT_NEEDS_QMAIN","-DQ_CREATOR_RUN","-DQT_ANNOTATE_FUNCTION(x)=__attribute__((annotate(#x)))","-ID:\\Qt\\Tools\\QtCreator\\share\\qtcreator\\cplusplus\\wrappedMingwHeaders","-ID:\\Qt\\Tools\\QtCreator\\share\\qtcreator\\cplusplus\\wrappedQtHeaders","-ID:\\Qt\\Tools\\QtCreator\\share\\qtcreator\\cplusplus\\wrappedQtHeaders\\QtCore","-ID:\\embeddedprojectgithhub\\TIC_TAK_TOE_PROJECT\\final","-ID:\\Qt\\6.9.1\\mingw_64\\include","-ID:\\Qt\\6.9.1\\mingw_64\\include\\QtWidgets","-ID:\\Qt\\6.9.1\\mingw_64\\include\\QtGui","-ID:\\Qt\\6.9.1\\mingw_64\\include\\QtCore","-ID:\\embeddedprojectgithhub\\TIC_TAK_TOE_PROJECT\\final\\build\\Desktop_Qt_6_9_1_MinGW_64_bit-Release\\release","-ID:\\embeddedprojectgithhub\\TIC_TAK_TOE_PROJECT\\final\\build\\Desktop_Qt_6_9_1_MinGW_64_bit-Release","-ID:\\Qt\\6.9.1\\mingw_64\\mkspecs\\win32-g++","-isystem","D:\\Qt\\Tools\\mingw1310_64\\lib\\gcc\\x86_64-w64-mingw32\\13.1.0\\include\\c++","-isystem","D:\\Qt\\Tools\\mingw1310_64\\lib\\gcc\\x86_64-w64-mingw32\\13.1.0\\include\\c++\\x86_64-w64-mingw32","-isystem","D:\\Qt\\Tools\\mingw1310_64\\lib\\gcc\\x86_64-w64-mingw32\\13.1.0\\include\\c++\\backward","-isystem","D:\\Qt\\Tools\\QtCreator\\bin\\clang\\lib\\clang\\19\\include","-isystem","D:\\Qt\\Tools\\mingw1310_64\\x86_64-w64-mingw32\\include","-fmessage-length=0","-fdiagnostics-show-note-include-stack","-fretain-comments-from-system-headers","-fmacro-backtrace-limit=0","-ferror-limit=1000","-x","c++-header","D:\\embeddedprojectgithhub\\TIC_TAK_TOE_PROJECT\\final\\Board.h"],"directory":"D:/embeddedprojectgithhub/TIC_TAK_TOE_PROJECT/final/build/Desktop_Qt_6_9_1_MinGW_64_bit-Release/.qtc_clangd","file":"D:/embeddedprojectgithhub/TIC_TAK_TOE_PROJECT/final/Board.h"},{"arguments":["clang","-Wno-documentation-unknown-command","-Wno-unknown-warning-option","-Wno-unknown-pragmas","-nostdinc","-nostdinc++","-std=gnu++1z","-Wall","-Wextra","-Wextra","-fexceptions","-mthreads","-fsyntax-only","-m64","--target=x86_64-w64-mingw32","-DUNICODE","-D_UNICODE","-DWIN32","-DMINGW_HAS_SECURE_API","-DQT_NO_DEBUG","-DQT_WIDGETS_LIB","-DQT_GUI_LIB","-DQT_CORE_LIB","-DQT_NEEDS_QMAIN","-DQ_CREATOR_RUN","-DQT_ANNOTATE_FUNCTION(x)=__attribute__((annotate(#x)))","-ID:\\Qt\\Tools\\QtCreator\\share\\qtcreator\\cplusplus\\wrappedMingwHeaders","-ID:\\Qt\\Tools\\QtCreator\\share\\qtcreator\\cplusplus\\wrappedQtHeaders","-ID:\\Qt\\Tools\\QtCreator\\share\\qtcreator\\cplusplus\\wrappedQtHeaders\\QtCore","-ID:\\embeddedprojectgithhub\\TIC_TAK_TOE_PROJECT\\final","-ID:\\Qt\\6.9.1\\mingw_64\\include","-ID:\\Qt\\6.9.1\\mingw_64\\include\\QtWidgets","-ID:\\Qt\\6.9.1\\mingw_64\\include\\QtGui","-ID:\\Qt\\6.9.1\\mingw_64\\include\\QtCore","-ID:\\embeddedprojectgithhub\\TIC_TAK_TOE_PROJECT\\final\\build\\Desktop_Qt_6_9_1_MinGW_64_bit-Release\\release","-ID:\\embeddedprojectgithhub\\TIC_TAK_TOE_PROJECT\\final\\build\\Desktop_Qt_6_9_1_MinGW_64_bit-Release","-ID:\\Qt\\6.9.1\\mingw_64\\mkspecs\\win32-g++","-isystem","D:\\Qt\\Tools\\mingw1310_64\\lib\\gcc\\x86_64-w64-mingw32\\13.1.0\\include\\c++","-isystem","D:\\Qt\\Tools\\mingw1310_64\\lib\\gcc\\x86_64-w64-mingw32\\13.1.0\\include\\c++\\x86_64-w64-mingw32","-isystem","D:\\Qt\\Tools\\mingw1310_64\\lib\\gcc\\x86_64-w64-mingw32\\13.1.0\\include\\c++\\backward","-isystem","D:\\Qt\\Tools\\QtCreator\\bin\\clang\\lib\\clang\\19\\include","-isystem","D:\\Qt\\Tools\\mingw1310_64\\x86_64-w64-mingw32\\include","-fmessage-length=0","-fdiagnostics-show-note-include-stack","-fretain-comments-from-system-headers","-fmacro-backtrace-limit=0","-ferror-limit=1000","-x","c++-header","D:\\embeddedprojectgithhub\\TIC_TAK_TOE_PROJECT\\final\\ai_opponent.h"],"directory":"D:/embeddedprojectgithhub/TIC_TAK_TOE_PROJECT/final/build/Desktop_Qt_6_9_1_MinGW_64_bit-Release/.qtc_clangd","file":"D:/embeddedprojectgithhub/TIC_TAK_TOE_PROJECT/final/ai_opponent.h"},{"arguments":["clang","-Wno-documentation-unknown-command","-Wno-unknown-warning-option","-Wno-unknown-pragmas","-nostdinc","-nostdinc++","-std=gnu++1z","-Wall","-Wextra","-Wextra","-fexceptions","-mthreads","-fsyntax-only","-m64","--target=x86_64-w64-mingw32","-DUNICODE","-D_UNICODE","-DWIN32","-DMINGW_HAS_SECURE_API","-DQT_NO_DEBUG","-DQT_WIDGETS_LIB","-DQT_GUI_LIB","-DQT_CORE_LIB","-DQT_NEEDS_QMAIN","-DQ_CREATOR_RUN","-DQT_ANNOTATE_FUNCTION(x)=__attribute__((annotate(#x)))","-ID:\\Qt\\Tools\\QtCreator\\share\\qtcreator\\cplusplus\\wrappedMingwHeaders","-ID:\\Qt\\Tools\\QtCreator\\share\\qtcreator\\cplusplus\\wrappedQtHeaders","-ID:\\Qt\\Tools\\QtCreator\\share\\qtcreator\\cplusplus\\wrappedQtHeaders\\QtCore","-ID:\\embeddedprojectgithhub\\TIC_TAK_TOE_PROJECT\\final","-ID:\\Qt\\6.9.1\\mingw_64\\include","-ID:\\Qt\\6.9.1\\mingw_64\\include\\QtWidgets","-ID:\\Qt\\6.9.1\\mingw_64\\include\\QtGui","-ID:\\Qt\\6.9.1\\mingw_64\\include\\QtCore","-ID:\\embeddedprojectgithhub\\TIC_TAK_TOE_PROJECT\\final\\build\\Desktop_Qt_6_9_1_MinGW_64_bit-Release\\release","-ID:\\embeddedprojectgithhub\\TIC_TAK_TOE_PROJECT\\final\\build\\Desktop_Qt_6_9_1_MinGW_64_bit-Release","-ID:\\Qt\\6.9.1\\mingw_64\\mkspecs\\win32-g++","-isystem","D:\\Qt\\Tools\\mingw1310_64\\lib\\gcc\\x86_64-w64-mingw32\\13.1.0\\include\\c++","-isystem","D:\\Qt\\Tools\\mingw1310_64\\lib\\gcc\\x86_64-w64-mingw32\\13.1.0\\include\\c++\\x86_64-w64-mingw32","-isystem","D:\\Qt\\Tools\\mingw1310_64\\lib\\gcc\\x86_64-w64-mingw32\\13.1.0\\include\\c++\\backward","-isystem","D:\\Qt\\Tools\\QtCreator\\bin\\clang\\lib\\clang\\19\\include","-isystem","D:\\Qt\\Tools\\mingw1310_64\\x86_64-w64-mingw32\\include","-fmessage-length=0","-fdiagnostics-show-note-include-stack","-fretain-comments-from-system-headers","-fmacro-backtrace-limit=0","-ferror-limit=1000","-x","c++-header","D:\\embeddedprojectgithhub\\TIC_TAK_TOE_PROJECT\\final\\codeverification.h"],"directory":"D:/embeddedprojectgithhub/TIC_TAK_TOE_PROJECT/final/build/Desktop_Qt_6_9_1_MinGW_64_bit-Release/.qtc_clangd","file":"D:/embeddedprojectgithhub/TIC_TAK_TOE_PROJECT/final/codeverification.h"},{"arguments":["clang","-Wno-documentation-unknown-command","-Wno-unknown-warning-option","-Wno-unknown-pragmas","-nostdinc","-nostdinc++","-std=gnu++1z","-Wall","-Wextra","-Wextra","-fexceptions","-mthreads","-fsyntax-only","-m64","--target=x86_64-w64-mingw32","-DUNICODE","-D_UNICODE","-DWIN32","-DMINGW_HAS_SECURE_API","-DQT_NO_DEBUG","-DQT_WIDGETS_LIB","-DQT_GUI_LIB","-DQT_CORE_LIB","-DQT_NEEDS_QMAIN","-DQ_CREATOR_RUN","-DQT_ANNOTATE_FUNCTION(x)=__attribute__((annotate(#x)))","-ID:\\Qt\\Tools\\QtCreator\\share\\qtcreator\\cplusplus\\wrappedMingwHeaders","-ID:\\Qt\\Tools\\QtCreator\\share\\qtcreator\\cplusplus\\wrappedQtHeaders","-ID:\\Qt\\Tools\\QtCreator\\share\\qtcreator\\cplusplus\\wrappedQtHeaders\\QtCore","-ID:\\embeddedprojectgithhub\\TIC_TAK_TOE_PROJECT\\final","-ID:\\Qt\\6.9.1\\mingw_64\\include","-ID:\\Qt\\6.9.1\\mingw_64\\include\\QtWidgets","-ID:\\Qt\\6.9.1\\mingw_64\\include\\QtGui","-ID:\\Qt\\6.9.1\\mingw_64\\include\\QtCore","-ID:\\embeddedprojectgithhub\\TIC_TAK_TOE_PROJECT\\final\\build\\Desktop_Qt_6_9_1_MinGW_64_bit-Release\\release","-ID:\\embeddedprojectgithhub\\TIC_TAK_TOE_PROJECT\\final\\build\\Desktop_Qt_6_9_1_MinGW_64_bit-Release","-ID:\\Qt\\6.9.1\\mingw_64\\mkspecs\\win32-g++","-isystem","D:\\Qt\\Tools\\mingw1310_64\\lib\\gcc\\x86_64-w64-mingw32\\13.1.0\\include\\c++","-isystem","D:\\Qt\\Tools\\mingw1310_64\\lib\\gcc\\x86_64-w64-mingw32\\13.1.0\\include\\c++\\x86_64-w64-mingw32","-isystem","D:\\Qt\\Tools\\mingw1310_64\\lib\\gcc\\x86_64-w64-mingw32\\13.1.0\\include\\c++\\backward","-isystem","D:\\Qt\\Tools\\QtCreator\\bin\\clang\\lib\\clang\\19\\include","-isystem","D:\\Qt\\Tools\\mingw1310_64\\x86_64-w64-mingw32\\include","-fmessage-length=0","-fdiagnostics-show-note-include-stack","-fretain-comments-from-system-headers","-fmacro-backtrace-limit=0","-ferror-limit=1000","-x","c++-header","D:\\embeddedprojectgithhub\\TIC_TAK_TOE_PROJECT\\final\\game.h"],"directory":"D:/embeddedprojectgithhub/TIC_TAK_TOE_PROJECT/final/build/Desktop_Qt_6_9_1_MinGW_64_bit-Release/.qtc_clangd","file":"D:/embeddedprojectgithhub/TIC_TAK_TOE_PROJECT/final/game.h"},{"arguments":["clang","-Wno-documentation-unknown-command","-Wno-unknown-warning-option","-Wno-unknown-pragmas","-nostdinc","-nostdinc++","-std=gnu++1z","-Wall","-Wextra","-Wextra","-fexceptions","-mthreads","-fsyntax-only","-m64","--target=x86_64-w64-mingw32","-DUNICODE","-D_UNICODE","-DWIN32","-DMINGW_HAS_SECURE_API","-DQT_NO_DEBUG","-DQT_WIDGETS_LIB","-DQT_GUI_LIB","-DQT_CORE_LIB","-DQT_NEEDS_QMAIN","-DQ_CREATOR_RUN","-DQT_ANNOTATE_FUNCTION(x)=__attribute__((annotate(#x)))","-ID:\\Qt\\Tools\\QtCreator\\share\\qtcreator\\cplusplus\\wrappedMingwHeaders","-ID:\\Qt\\Tools\\QtCreator\\share\\qtcreator\\cplusplus\\wrappedQtHeaders","-ID:\\Qt\\Tools\\QtCreator\\share\\qtcreator\\cplusplus\\wrappedQtHeaders\\QtCore","-ID:\\embeddedprojectgithhub\\TIC_TAK_TOE_PROJECT\\final","-ID:\\Qt\\6.9.1\\mingw_64\\include","-ID:\\Qt\\6.9.1\\mingw_64\\include\\QtWidgets","-ID:\\Qt\\6.9.1\\mingw_64\\include\\QtGui","-ID:\\Qt\\6.9.1\\mingw_64\\include\\QtCore","-ID:\\embeddedprojectgithhub\\TIC_TAK_TOE_PROJECT\\final\\build\\Desktop_Qt_6_9_1_MinGW_64_bit-Release\\release","-ID:\\embeddedprojectgithhub\\TIC_TAK_TOE_PROJECT\\final\\build\\Desktop_Qt_6_9_1_MinGW_64_bit-Release","-ID:\\Qt\\6.9.1\\mingw_64\\mkspecs\\win32-g++","-isystem","D:\\Qt\\Tools\\mingw1310_64\\lib\\gcc\\x86_64-w64-mingw32\\13.1.0\\include\\c++","-isystem","D:\\Qt\\Tools\\mingw1310_64\\lib\\gcc\\x86_64-w64-mingw32\\13.1.0\\include\\c++\\x86_64-w64-mingw32","-isystem","D:\\Qt\\Tools\\mingw1310_64\\lib\\gcc\\x86_64-w64-mingw32\\13.1.0\\include\\c++\\backward","-isystem","D:\\Qt\\Tools\\QtCreator\\bin\\clang\\lib\\clang\\19\\include","-isystem","D:\\Qt\\Tools\\mingw1310_64\\x86_64-w64-mingw32\\include","-fmessage-length=0","-fdiagnostics-show-note-include-stack","-fretain-comments-from-system-headers","-fmacro-backtrace-limit=0","-ferror-limit=1000","-x","c++-header","D:\\embeddedprojectgithhub\\TIC_TAK_TOE_PROJECT\\final\\gamelogic.h"],"directory":"D:/embeddedprojectgithhub/TIC_TAK_TOE_PROJECT/final/build/Desktop_Qt_6_9_1_MinGW_64_bit-Release/.qtc_clangd","file":"D:/embeddedprojectgithhub/TIC_TAK_TOE_PROJECT/final/gamelogic.h"},{"arguments":["clang","-Wno-documentation-unknown-command","-Wno-unknown-warning-option","-Wno-unknown-pragmas","-nostdinc","-nostdinc++","-std=gnu++1z","-Wall","-Wextra","-Wextra","-fexceptions","-mthreads","-fsyntax-only","-m64","--target=x86_64-w64-mingw32","-DUNICODE","-D_UNICODE","-DWIN32","-DMINGW_HAS_SECURE_API","-DQT_NO_DEBUG","-DQT_WIDGETS_LIB","-DQT_GUI_LIB","-DQT_CORE_LIB","-DQT_NEEDS_QMAIN","-DQ_CREATOR_RUN","-DQT_ANNOTATE_FUNCTION(x)=__attribute__((annotate(#x)))","-ID:\\Qt\\Tools\\QtCreator\\share\\qtcreator\\cplusplus\\wrappedMingwHeaders","-ID:\\Qt\\Tools\\QtCreator\\share\\qtcreator\\cplusplus\\wrappedQtHeaders","-ID:\\Qt\\Tools\\QtCreator\\share\\qtcreator\\cplusplus\\wrappedQtHeaders\\QtCore","-ID:\\embeddedprojectgithhub\\TIC_TAK_TOE_PROJECT\\final","-ID:\\Qt\\6.9.1\\mingw_64\\include","-ID:\\Qt\\6.9.1\\mingw_64\\include\\QtWidgets","-ID:\\Qt\\6.9.1\\mingw_64\\include\\QtGui","-ID:\\Qt\\6.9.1\\mingw_64\\include\\QtCore","-ID:\\embeddedprojectgithhub\\TIC_TAK_TOE_PROJECT\\final\\build\\Desktop_Qt_6_9_1_MinGW_64_bit-Release\\release","-ID:\\embeddedprojectgithhub\\TIC_TAK_TOE_PROJECT\\final\\build\\Desktop_Qt_6_9_1_MinGW_64_bit-Release","-ID:\\Qt\\6.9.1\\mingw_64\\mkspecs\\win32-g++","-isystem","D:\\Qt\\Tools\\mingw1310_64\\lib\\gcc\\x86_64-w64-mingw32\\13.1.0\\include\\c++","-isystem","D:\\Qt\\Tools\\mingw1310_64\\lib\\gcc\\x86_64-w64-mingw32\\13.1.0\\include\\c++\\x86_64-w64-mingw32","-isystem","D:\\Qt\\Tools\\mingw1310_64\\lib\\gcc\\x86_64-w64-mingw32\\13.1.0\\include\\c++\\backward","-isystem","D:\\Qt\\Tools\\QtCreator\\bin\\clang\\lib\\clang\\19\\include","-isystem","D:\\Qt\\Tools\\mingw1310_64\\x86_64-w64-mingw32\\include","-fmessage-length=0","-fdiagnostics-show-note-include-stack","-fretain-comments-from-system-headers","-fmacro-backtrace-limit=0","-ferror-limit=1000","-x","c++-header","D:\\embeddedprojectgithhub\\TIC_TAK_TOE_PROJECT\\final\\gamemanager.h"],"directory":"D:/embeddedprojectgithhub/TIC_TAK_TOE_PROJECT/final/build/Desktop_Qt_6_9_1_MinGW_64_bit-Release/.qtc_clangd","file":"D:/embeddedprojectgithhub/TIC_TAK_TOE_PROJECT/final/gamemanager.h"},{"arguments":["clang","-Wno-documentation-unknown-command","-Wno-unknown-warning-option","-Wno-unknown-pragmas","-nostdinc","-nostdinc++","-std=gnu++1z","-Wall","-Wextra","-Wextra","-fexceptions","-mthreads","-fsyntax-only","-m64","--target=x86_64-w64-mingw32","-DUNICODE","-D_UNICODE","-DWIN32","-DMINGW_HAS_SECURE_API","-DQT_NO_DEBUG","-DQT_WIDGETS_LIB","-DQT_GUI_LIB","-DQT_CORE_LIB","-DQT_NEEDS_QMAIN","-DQ_CREATOR_RUN","-DQT_ANNOTATE_FUNCTION(x)=__attribute__((annotate(#x)))","-ID:\\Qt\\Tools\\QtCreator\\share\\qtcreator\\cplusplus\\wrappedMingwHeaders","-ID:\\Qt\\Tools\\QtCreator\\share\\qtcreator\\cplusplus\\wrappedQtHeaders","-ID:\\Qt\\Tools\\QtCreator\\share\\qtcreator\\cplusplus\\wrappedQtHeaders\\QtCore","-ID:\\embeddedprojectgithhub\\TIC_TAK_TOE_PROJECT\\final","-ID:\\Qt\\6.9.1\\mingw_64\\include","-ID:\\Qt\\6.9.1\\mingw_64\\include\\QtWidgets","-ID:\\Qt\\6.9.1\\mingw_64\\include\\QtGui","-ID:\\Qt\\6.9.1\\mingw_64\\include\\QtCore","-ID:\\embeddedprojectgithhub\\TIC_TAK_TOE_PROJECT\\final\\build\\Desktop_Qt_6_9_1_MinGW_64_bit-Release\\release","-ID:\\embeddedprojectgithhub\\TIC_TAK_TOE_PROJECT\\final\\build\\Desktop_Qt_6_9_1_MinGW_64_bit-Release","-ID:\\Qt\\6.9.1\\mingw_64\\mkspecs\\win32-g++","-isystem","D:\\Qt\\Tools\\mingw1310_64\\lib\\gcc\\x86_64-w64-mingw32\\13.1.0\\include\\c++","-isystem","D:\\Qt\\Tools\\mingw1310_64\\lib\\gcc\\x86_64-w64-mingw32\\13.1.0\\include\\c++\\x86_64-w64-mingw32","-isystem","D:\\Qt\\Tools\\mingw1310_64\\lib\\gcc\\x86_64-w64-mingw32\\13.1.0\\include\\c++\\backward","-isystem","D:\\Qt\\Tools\\QtCreator\\bin\\clang\\lib\\clang\\19\\include","-isystem","D:\\Qt\\Tools\\mingw1310_64\\x86_64-w64-mingw32\\include","-fmessage-length=0","-fdiagnostics-show-note-include-stack","-fretain-comments-from-system-headers","-fmacro-backtrace-limit=0","-ferror-limit=1000","-x","c++-header","D:\\embeddedprojectgithhub\\TIC_TAK_TOE_PROJECT\\final\\globals.h"],"directory":"D:/embeddedprojectgithhub/TIC_TAK_TOE_PROJECT/final/build/Desktop_Qt_6_9_1_MinGW_64_bit-Release/.qtc_clangd","file":"D:/embeddedprojectgithhub/TIC_TAK_TOE_PROJECT/final/globals.h"},{"arguments":["clang","-Wno-documentation-unknown-command","-Wno-unknown-warning-option","-Wno-unknown-pragmas","-nostdinc","-nostdinc++","-std=gnu++1z","-Wall","-Wextra","-Wextra","-fexceptions","-mthreads","-fsyntax-only","-m64","--target=x86_64-w64-mingw32","-DUNICODE","-D_UNICODE","-DWIN32","-DMINGW_HAS_SECURE_API","-DQT_NO_DEBUG","-DQT_WIDGETS_LIB","-DQT_GUI_LIB","-DQT_CORE_LIB","-DQT_NEEDS_QMAIN","-DQ_CREATOR_RUN","-DQT_ANNOTATE_FUNCTION(x)=__attribute__((annotate(#x)))","-ID:\\Qt\\Tools\\QtCreator\\share\\qtcreator\\cplusplus\\wrappedMingwHeaders","-ID:\\Qt\\Tools\\QtCreator\\share\\qtcreator\\cplusplus\\wrappedQtHeaders","-ID:\\Qt\\Tools\\QtCreator\\share\\qtcreator\\cplusplus\\wrappedQtHeaders\\QtCore","-ID:\\embeddedprojectgithhub\\TIC_TAK_TOE_PROJECT\\final","-ID:\\Qt\\6.9.1\\mingw_64\\include","-ID:\\Qt\\6.9.1\\mingw_64\\include\\QtWidgets","-ID:\\Qt\\6.9.1\\mingw_64\\include\\QtGui","-ID:\\Qt\\6.9.1\\mingw_64\\include\\QtCore","-ID:\\embeddedprojectgithhub\\TIC_TAK_TOE_PROJECT\\final\\build\\Desktop_Qt_6_9_1_MinGW_64_bit-Release\\release","-ID:\\embeddedprojectgithhub\\TIC_TAK_TOE_PROJECT\\final\\build\\Desktop_Qt_6_9_1_MinGW_64_bit-Release","-ID:\\Qt\\6.9.1\\mingw_64\\mkspecs\\win32-g++","-isystem","D:\\Qt\\Tools\\mingw1310_64\\lib\\gcc\\x86_64-w64-mingw32\\13.1.0\\include\\c++","-isystem","D:\\Qt\\Tools\\mingw1310_64\\lib\\gcc\\x86_64-w64-mingw32\\13.1.0\\include\\c++\\x86_64-w64-mingw32","-isystem","D:\\Qt\\Tools\\mingw1310_64\\lib\\gcc\\x86_64-w64-mingw32\\13.1.0\\include\\c++\\backward","-isystem","D:\\Qt\\Tools\\QtCreator\\bin\\clang\\lib\\clang\\19\\include","-isystem","D:\\Qt\\Tools\\mingw1310_64\\x86_64-w64-mingw32\\include","-fmessage-length=0","-fdiagnostics-show-note-include-stack","-fretain-comments-from-system-headers","-fmacro-backtrace-limit=0","-ferror-limit=1000","-x","c++-header","D:\\embeddedprojectgithhub\\TIC_TAK_TOE_PROJECT\\final\\historymanager.h"],"directory":"D:/embeddedprojectgithhub/TIC_TAK_TOE_PROJECT/final/build/Desktop_Qt_6_9_1_MinGW_64_bit-Release/.qtc_clangd","file":"D:/embeddedprojectgithhub/TIC_TAK_TOE_PROJECT/final/historymanager.h"},{"arguments":["clang","-Wno-documentation-unknown-command","-Wno-unknown-warning-option","-Wno-unknown-pragmas","-nostdinc","-nostdinc++","-std=gnu++1z","-Wall","-Wextra","-Wextra","-fexceptions","-mthreads","-fsyntax-only","-m64","--target=x86_64-w64-mingw32","-DUNICODE","-D_UNICODE","-DWIN32","-DMINGW_HAS_SECURE_API","-DQT_NO_DEBUG","-DQT_WIDGETS_LIB","-DQT_GUI_LIB","-DQT_CORE_LIB","-DQT_NEEDS_QMAIN","-DQ_CREATOR_RUN","-DQT_ANNOTATE_FUNCTION(x)=__attribute__((annotate(#x)))","-ID:\\Qt\\Tools\\QtCreator\\share\\qtcreator\\cplusplus\\wrappedMingwHeaders","-ID:\\Qt\\Tools\\QtCreator\\share\\qtcreator\\cplusplus\\wrappedQtHeaders","-ID:\\Qt\\Tools\\QtCreator\\share\\qtcreator\\cplusplus\\wrappedQtHeaders\\QtCore","-ID:\\embeddedprojectgithhub\\TIC_TAK_TOE_PROJECT\\final","-ID:\\Qt\\6.9.1\\mingw_64\\include","-ID:\\Qt\\6.9.1\\mingw_64\\include\\QtWidgets","-ID:\\Qt\\6.9.1\\mingw_64\\include\\QtGui","-ID:\\Qt\\6.9.1\\mingw_64\\include\\QtCore","-ID:\\embeddedprojectgithhub\\TIC_TAK_TOE_PROJECT\\final\\build\\Desktop_Qt_6_9_1_MinGW_64_bit-Release\\release","-ID:\\embeddedprojectgithhub\\TIC_TAK_TOE_PROJECT\\final\\build\\Desktop_Qt_6_9_1_MinGW_64_bit-Release","-ID:\\Qt\\6.9.1\\mingw_64\\mkspecs\\win32-g++","-isystem","D:\\Qt\\Tools\\mingw1310_64\\lib\\gcc\\x86_64-w64-mingw32\\13.1.0\\include\\c++","-isystem","D:\\Qt\\Tools\\mingw1310_64\\lib\\gcc\\x86_64-w64-mingw32\\13.1.0\\include\\c++\\x86_64-w64-mingw32","-isystem","D:\\Qt\\Tools\\mingw1310_64\\lib\\gcc\\x86_64-w64-mingw32\\13.1.0\\include\\c++\\backward","-isystem","D:\\Qt\\Tools\\QtCreator\\bin\\clang\\lib\\clang\\19\\include","-isystem","D:\\Qt\\Tools\\mingw1310_64\\x86_64-w64-mingw32\\include","-fmessage-length=0","-fdiagnostics-show-note-include-stack","-fretain-comments-from-system-headers","-fmacro-backtrace-limit=0","-ferror-limit=1000","-x","c++-header","D:\\embeddedprojectgithhub\\TIC_TAK_TOE_PROJECT\\final\\home.h"],"directory":"D:/embeddedprojectgithhub/TIC_TAK_TOE_PROJECT/final/build/Desktop_Qt_6_9_1_MinGW_64_bit-Release/.qtc_clangd","file":"D:/embeddedprojectgithhub/TIC_TAK_TOE_PROJECT/final/home.h"},{"arguments":["clang","-Wno-documentation-unknown-command","-Wno-unknown-warning-option","-Wno-unknown-pragmas","-nostdinc","-nostdinc++","-std=gnu++1z","-Wall","-Wextra","-Wextra","-fexceptions","-mthreads","-fsyntax-only","-m64","--target=x86_64-w64-mingw32","-DUNICODE","-D_UNICODE","-DWIN32","-DMINGW_HAS_SECURE_API","-DQT_NO_DEBUG","-DQT_WIDGETS_LIB","-DQT_GUI_LIB","-DQT_CORE_LIB","-DQT_NEEDS_QMAIN","-DQ_CREATOR_RUN","-DQT_ANNOTATE_FUNCTION(x)=__attribute__((annotate(#x)))","-ID:\\Qt\\Tools\\QtCreator\\share\\qtcreator\\cplusplus\\wrappedMingwHeaders","-ID:\\Qt\\Tools\\QtCreator\\share\\qtcreator\\cplusplus\\wrappedQtHeaders","-ID:\\Qt\\Tools\\QtCreator\\share\\qtcreator\\cplusplus\\wrappedQtHeaders\\QtCore","-ID:\\embeddedprojectgithhub\\TIC_TAK_TOE_PROJECT\\final","-ID:\\Qt\\6.9.1\\mingw_64\\include","-ID:\\Qt\\6.9.1\\mingw_64\\include\\QtWidgets","-ID:\\Qt\\6.9.1\\mingw_64\\include\\QtGui","-ID:\\Qt\\6.9.1\\mingw_64\\include\\QtCore","-ID:\\embeddedprojectgithhub\\TIC_TAK_TOE_PROJECT\\final\\build\\Desktop_Qt_6_9_1_MinGW_64_bit-Release\\release","-ID:\\embeddedprojectgithhub\\TIC_TAK_TOE_PROJECT\\final\\build\\Desktop_Qt_6_9_1_MinGW_64_bit-Release","-ID:\\Qt\\6.9.1\\mingw_64\\mkspecs\\win32-g++","-isystem","D:\\Qt\\Tools\\mingw1310_64\\lib\\gcc\\x86_64-w64-mingw32\\13.1.0\\include\\c++","-isystem","D:\\Qt\\Tools\\mingw1310_64\\lib\\gcc\\x86_64-w64-mingw32\\13.1.0\\include\\c++\\x86_64-w64-mingw32","-isystem","D:\\Qt\\Tools\\mingw1310_64\\lib\\gcc\\x86_64-w64-mingw32\\13.1.0\\include\\c++\\backward","-isystem","D:\\Qt\\Tools\\QtCreator\\bin\\clang\\lib\\clang\\19\\include","-isystem","D:\\Qt\\Tools\\mingw1310_64\\x86_64-w64-mingw32\\include","-fmessage-length=0","-fdiagnostics-show-note-include-stack","-fretain-comments-from-system-headers","-fmacro-backtrace-limit=0","-ferror-limit=1000","-x","c++-header","D:\\embeddedprojectgithhub\\TIC_TAK_TOE_PROJECT\\final\\login.h"],"directory":"D:/embeddedprojectgithhub/TIC_TAK_TOE_PROJECT/final/build/Desktop_Qt_6_9_1_MinGW_64_bit-Release/.qtc_clangd","file":"D:/embeddedprojectgithhub/TIC_TAK_TOE_PROJECT/final/login.h"},{"arguments":["clang","-Wno-documentation-unknown-command","-Wno-unknown-warning-option","-Wno-unknown-pragmas","-nostdinc","-nostdinc++","-std=gnu++1z","-Wall","-Wextra","-Wextra","-fexceptions","-mthreads","-fsyntax-only","-m64","--target=x86_64-w64-mingw32","-DUNICODE","-D_UNICODE","-DWIN32","-DMINGW_HAS_SECURE_API","-DQT_NO_DEBUG","-DQT_WIDGETS_LIB","-DQT_GUI_LIB","-DQT_CORE_LIB","-DQT_NEEDS_QMAIN","-DQ_CREATOR_RUN","-DQT_ANNOTATE_FUNCTION(x)=__attribute__((annotate(#x)))","-ID:\\Qt\\Tools\\QtCreator\\share\\qtcreator\\cplusplus\\wrappedMingwHeaders","-ID:\\Qt\\Tools\\QtCreator\\share\\qtcreator\\cplusplus\\wrappedQtHeaders","-ID:\\Qt\\Tools\\QtCreator\\share\\qtcreator\\cplusplus\\wrappedQtHeaders\\QtCore","-ID:\\embeddedprojectgithhub\\TIC_TAK_TOE_PROJECT\\final","-ID:\\Qt\\6.9.1\\mingw_64\\include","-ID:\\Qt\\6.9.1\\mingw_64\\include\\QtWidgets","-ID:\\Qt\\6.9.1\\mingw_64\\include\\QtGui","-ID:\\Qt\\6.9.1\\mingw_64\\include\\QtCore","-ID:\\embeddedprojectgithhub\\TIC_TAK_TOE_PROJECT\\final\\build\\Desktop_Qt_6_9_1_MinGW_64_bit-Release\\release","-ID:\\embeddedprojectgithhub\\TIC_TAK_TOE_PROJECT\\final\\build\\Desktop_Qt_6_9_1_MinGW_64_bit-Release","-ID:\\Qt\\6.9.1\\mingw_64\\mkspecs\\win32-g++","-isystem","D:\\Qt\\Tools\\mingw1310_64\\lib\\gcc\\x86_64-w64-mingw32\\13.1.0\\include\\c++","-isystem","D:\\Qt\\Tools\\mingw1310_64\\lib\\gcc\\x86_64-w64-mingw32\\13.1.0\\include\\c++\\x86_64-w64-mingw32","-isystem","D:\\Qt\\Tools\\mingw1310_64\\lib\\gcc\\x86_64-w64-mingw32\\13.1.0\\include\\c++\\backward","-isystem","D:\\Qt\\Tools\\QtCreator\\bin\\clang\\lib\\clang\\19\\include","-isystem","D:\\Qt\\Tools\\mingw1310_64\\x86_64-w64-mingw32\\include","-fmessage-length=0","-fdiagnostics-show-note-include-stack","-fretain-comments-from-system-headers","-fmacro-backtrace-limit=0","-ferror-limit=1000","-x","c++-header","D:\\embeddedprojectgithhub\\TIC_TAK_TOE_PROJECT\\final\\mainwindow.h"],"directory":"D:/embeddedprojectgithhub/TIC_TAK_TOE_PROJECT/final/build/Desktop_Qt_6_9_1_MinGW_64_bit-Release/.qtc_clangd","file":"D:/embeddedprojectgithhub/TIC_TAK_TOE_PROJECT/final/mainwindow.h"},{"arguments":["clang","-Wno-documentation-unknown-command","-Wno-unknown-warning-option","-Wno-unknown-pragmas","-nostdinc","-nostdinc++","-std=gnu++1z","-Wall","-Wextra","-Wextra","-fexceptions","-mthreads","-fsyntax-only","-m64","--target=x86_64-w64-mingw32","-DUNICODE","-D_UNICODE","-DWIN32","-DMINGW_HAS_SECURE_API","-DQT_NO_DEBUG","-DQT_WIDGETS_LIB","-DQT_GUI_LIB","-DQT_CORE_LIB","-DQT_NEEDS_QMAIN","-DQ_CREATOR_RUN","-DQT_ANNOTATE_FUNCTION(x)=__attribute__((annotate(#x)))","-ID:\\Qt\\Tools\\QtCreator\\share\\qtcreator\\cplusplus\\wrappedMingwHeaders","-ID:\\Qt\\Tools\\QtCreator\\share\\qtcreator\\cplusplus\\wrappedQtHeaders","-ID:\\Qt\\Tools\\QtCreator\\share\\qtcreator\\cplusplus\\wrappedQtHeaders\\QtCore","-ID:\\embeddedprojectgithhub\\TIC_TAK_TOE_PROJECT\\final","-ID:\\Qt\\6.9.1\\mingw_64\\include","-ID:\\Qt\\6.9.1\\mingw_64\\include\\QtWidgets","-ID:\\Qt\\6.9.1\\mingw_64\\include\\QtGui","-ID:\\Qt\\6.9.1\\mingw_64\\include\\QtCore","-ID:\\embeddedprojectgithhub\\TIC_TAK_TOE_PROJECT\\final\\build\\Desktop_Qt_6_9_1_MinGW_64_bit-Release\\release","-ID:\\embeddedprojectgithhub\\TIC_TAK_TOE_PROJECT\\final\\build\\Desktop_Qt_6_9_1_MinGW_64_bit-Release","-ID:\\Qt\\6.9.1\\mingw_64\\mkspecs\\win32-g++","-isystem","D:\\Qt\\Tools\\mingw1310_64\\lib\\gcc\\x86_64-w64-mingw32\\13.1.0\\include\\c++","-isystem","D:\\Qt\\Tools\\mingw1310_64\\lib\\gcc\\x86_64-w64-mingw32\\13.1.0\\include\\c++\\x86_64-w64-mingw32","-isystem","D:\\Qt\\Tools\\mingw1310_64\\lib\\gcc\\x86_64-w64-mingw32\\13.1.0\\include\\c++\\backward","-isystem","D:\\Qt\\Tools\\QtCreator\\bin\\clang\\lib\\clang\\19\\include","-isystem","D:\\Qt\\Tools\\mingw1310_64\\x86_64-w64-mingw32\\include","-fmessage-length=0","-fdiagnostics-show-note-include-stack","-fretain-comments-from-system-headers","-fmacro-backtrace-limit=0","-ferror-limit=1000","-x","c++-header","D:\\embeddedprojectgithhub\\TIC_TAK_TOE_PROJECT\\final\\playboard.h"],"directory":"D:/embeddedprojectgithhub/TIC_TAK_TOE_PROJECT/final/build/Desktop_Qt_6_9_1_MinGW_64_bit-Release/.qtc_clangd","file":"D:/embeddedprojectgithhub/TIC_TAK_TOE_PROJECT/final/playboard.h"},{"arguments":["clang","-Wno-documentation-unknown-command","-Wno-unknown-warning-option","-Wno-unknown-pragmas","-nostdinc","-nostdinc++","-std=gnu++1z","-Wall","-Wextra","-Wextra","-fexceptions","-mthreads","-fsyntax-only","-m64","--target=x86_64-w64-mingw32","-DUNICODE","-D_UNICODE","-DWIN32","-DMINGW_HAS_SECURE_API","-DQT_NO_DEBUG","-DQT_WIDGETS_LIB","-DQT_GUI_LIB","-DQT_CORE_LIB","-DQT_NEEDS_QMAIN","-DQ_CREATOR_RUN","-DQT_ANNOTATE_FUNCTION(x)=__attribute__((annotate(#x)))","-ID:\\Qt\\Tools\\QtCreator\\share\\qtcreator\\cplusplus\\wrappedMingwHeaders","-ID:\\Qt\\Tools\\QtCreator\\share\\qtcreator\\cplusplus\\wrappedQtHeaders","-ID:\\Qt\\Tools\\QtCreator\\share\\qtcreator\\cplusplus\\wrappedQtHeaders\\QtCore","-ID:\\embeddedprojectgithhub\\TIC_TAK_TOE_PROJECT\\final","-ID:\\Qt\\6.9.1\\mingw_64\\include","-ID:\\Qt\\6.9.1\\mingw_64\\include\\QtWidgets","-ID:\\Qt\\6.9.1\\mingw_64\\include\\QtGui","-ID:\\Qt\\6.9.1\\mingw_64\\include\\QtCore","-ID:\\embeddedprojectgithhub\\TIC_TAK_TOE_PROJECT\\final\\build\\Desktop_Qt_6_9_1_MinGW_64_bit-Release\\release","-ID:\\embeddedprojectgithhub\\TIC_TAK_TOE_PROJECT\\final\\build\\Desktop_Qt_6_9_1_MinGW_64_bit-Release","-ID:\\Qt\\6.9.1\\mingw_64\\mkspecs\\win32-g++","-isystem","D:\\Qt\\Tools\\mingw1310_64\\lib\\gcc\\x86_64-w64-mingw32\\13.1.0\\include\\c++","-isystem","D:\\Qt\\Tools\\mingw1310_64\\lib\\gcc\\x86_64-w64-mingw32\\13.1.0\\include\\c++\\x86_64-w64-mingw32","-isystem","D:\\Qt\\Tools\\mingw1310_64\\lib\\gcc\\x86_64-w64-mingw32\\13.1.0\\include\\c++\\backward","-isystem","D:\\Qt\\Tools\\QtCreator\\bin\\clang\\lib\\clang\\19\\include","-isystem","D:\\Qt\\Tools\\mingw1310_64\\x86_64-w64-mingw32\\include","-fmessage-length=0","-fdiagnostics-show-note-include-stack","-fretain-comments-from-system-headers","-fmacro-backtrace-limit=0","-ferror-limit=1000","-x","c++-header","D:\\embeddedprojectgithhub\\TIC_TAK_TOE_PROJECT\\final\\playermanager.h"],"directory":"D:/embeddedprojectgithhub/TIC_TAK_TOE_PROJECT/final/build/Desktop_Qt_6_9_1_MinGW_64_bit-Release/.qtc_clangd","file":"D:/embeddedprojectgithhub/TIC_TAK_TOE_PROJECT/final/playermanager.h"},{"arguments":["clang","-Wno-documentation-unknown-command","-Wno-unknown-warning-option","-Wno-unknown-pragmas","-nostdinc","-nostdinc++","-std=gnu++1z","-Wall","-Wextra","-Wextra","-fexceptions","-mthreads","-fsyntax-only","-m64","--target=x86_64-w64-mingw32","-DUNICODE","-D_UNICODE","-DWIN32","-DMINGW_HAS_SECURE_API","-DQT_NO_DEBUG","-DQT_WIDGETS_LIB","-DQT_GUI_LIB","-DQT_CORE_LIB","-DQT_NEEDS_QMAIN","-DQ_CREATOR_RUN","-DQT_ANNOTATE_FUNCTION(x)=__attribute__((annotate(#x)))","-ID:\\Qt\\Tools\\QtCreator\\share\\qtcreator\\cplusplus\\wrappedMingwHeaders","-ID:\\Qt\\Tools\\QtCreator\\share\\qtcreator\\cplusplus\\wrappedQtHeaders","-ID:\\Qt\\Tools\\QtCreator\\share\\qtcreator\\cplusplus\\wrappedQtHeaders\\QtCore","-ID:\\embeddedprojectgithhub\\TIC_TAK_TOE_PROJECT\\final","-ID:\\Qt\\6.9.1\\mingw_64\\include","-ID:\\Qt\\6.9.1\\mingw_64\\include\\QtWidgets","-ID:\\Qt\\6.9.1\\mingw_64\\include\\QtGui","-ID:\\Qt\\6.9.1\\mingw_64\\include\\QtCore","-ID:\\embeddedprojectgithhub\\TIC_TAK_TOE_PROJECT\\final\\build\\Desktop_Qt_6_9_1_MinGW_64_bit-Release\\release","-ID:\\embeddedprojectgithhub\\TIC_TAK_TOE_PROJECT\\final\\build\\Desktop_Qt_6_9_1_MinGW_64_bit-Release","-ID:\\Qt\\6.9.1\\mingw_64\\mkspecs\\win32-g++","-isystem","D:\\Qt\\Tools\\mingw1310_64\\lib\\gcc\\x86_64-w64-mingw32\\13.1.0\\include\\c++","-isystem","D:\\Qt\\Tools\\mingw1310_64\\lib\\gcc\\x86_64-w64-mingw32\\13.1.0\\include\\c++\\x86_64-w64-mingw32","-isystem","D:\\Qt\\Tools\\mingw1310_64\\lib\\gcc\\x86_64-w64-mingw32\\13.1.0\\include\\c++\\backward","-isystem","D:\\Qt\\Tools\\QtCreator\\bin\\clang\\lib\\clang\\19\\include","-isystem","D:\\Qt\\Tools\\mingw1310_64\\x86_64-w64-mingw32\\include","-fmessage-length=0","-fdiagnostics-show-note-include-stack","-fretain-comments-from-system-headers","-fmacro-backtrace-limit=0","-ferror-limit=1000","-x","c++-header","D:\\embeddedprojectgithhub\\TIC_TAK_TOE_PROJECT\\final\\replayboard.h"],"directory":"D:/embeddedprojectgithhub/TIC_TAK_TOE_PROJECT/final/build/Desktop_Qt_6_9_1_MinGW_64_bit-Release/.qtc_clangd","file":"D:/embeddedprojectgithhub/TIC_TAK_TOE_PROJECT/final/replayboard.h"},{"arguments":["clang","-Wno-documentation-unknown-command","-Wno-unknown-warning-option","-Wno-unknown-pragmas","-nostdinc","-nostdinc++","-std=gnu++1z","-Wall","-Wextra","-Wextra","-fexceptions","-mthreads","-fsyntax-only","-m64","--target=x86_64-w64-mingw32","-DUNICODE","-D_UNICODE","-DWIN32","-DMINGW_HAS_SECURE_API","-DQT_NO_DEBUG","-DQT_WIDGETS_LIB","-DQT_GUI_LIB","-DQT_CORE_LIB","-DQT_NEEDS_QMAIN","-DQ_CREATOR_RUN","-DQT_ANNOTATE_FUNCTION(x)=__attribute__((annotate(#x)))","-ID:\\Qt\\Tools\\QtCreator\\share\\qtcreator\\cplusplus\\wrappedMingwHeaders","-ID:\\Qt\\Tools\\QtCreator\\share\\qtcreator\\cplusplus\\wrappedQtHeaders","-ID:\\Qt\\Tools\\QtCreator\\share\\qtcreator\\cplusplus\\wrappedQtHeaders\\QtCore","-ID:\\embeddedprojectgithhub\\TIC_TAK_TOE_PROJECT\\final","-ID:\\Qt\\6.9.1\\mingw_64\\include","-ID:\\Qt\\6.9.1\\mingw_64\\include\\QtWidgets","-ID:\\Qt\\6.9.1\\mingw_64\\include\\QtGui","-ID:\\Qt\\6.9.1\\mingw_64\\include\\QtCore","-ID:\\embeddedprojectgithhub\\TIC_TAK_TOE_PROJECT\\final\\build\\Desktop_Qt_6_9_1_MinGW_64_bit-Release\\release","-ID:\\embeddedprojectgithhub\\TIC_TAK_TOE_PROJECT\\final\\build\\Desktop_Qt_6_9_1_MinGW_64_bit-Release","-ID:\\Qt\\6.9.1\\mingw_64\\mkspecs\\win32-g++","-isystem","D:\\Qt\\Tools\\mingw1310_64\\lib\\gcc\\x86_64-w64-mingw32\\13.1.0\\include\\c++","-isystem","D:\\Qt\\Tools\\mingw1310_64\\lib\\gcc\\x86_64-w64-mingw32\\13.1.0\\include\\c++\\x86_64-w64-mingw32","-isystem","D:\\Qt\\Tools\\mingw1310_64\\lib\\gcc\\x86_64-w64-mingw32\\13.1.0\\include\\c++\\backward","-isystem","D:\\Qt\\Tools\\QtCreator\\bin\\clang\\lib\\clang\\19\\include","-isystem","D:\\Qt\\Tools\\mingw1310_64\\x86_64-w64-mingw32\\include","-fmessage-length=0","-fdiagnostics-show-note-include-stack","-fretain-comments-from-system-headers","-fmacro-backtrace-limit=0","-ferror-limit=1000","-x","c++-header","D:\\embeddedprojectgithhub\\TIC_TAK_TOE_PROJECT\\final\\sessiontimer.h"],"directory":"D:/embeddedprojectgithhub/TIC_TAK_TOE_PROJECT/final/build/Desktop_Qt_6_9_1_MinGW_64_bit-Release/.qtc_clangd","file":"D:/embeddedprojectgithhub/TIC_TAK_TOE_PROJECT/final/sessiontimer.h"},{"arguments":["clang","-Wno-documentation-unknown-command","-Wno-unknown-warning-option","-Wno-unknown-pragmas","-nostdinc","-nostdinc++","-std=gnu++1z","-Wall","-Wextra","-Wextra","-fexceptions","-mthreads","-fsyntax-only","-m64","--target=x86_64-w64-mingw32","-DUNICODE","-D_UNICODE","-DWIN32","-DMINGW_HAS_SECURE_API","-DQT_NO_DEBUG","-DQT_WIDGETS_LIB","-DQT_GUI_LIB","-DQT_CORE_LIB","-DQT_NEEDS_QMAIN","-DQ_CREATOR_RUN","-DQT_ANNOTATE_FUNCTION(x)=__attribute__((annotate(#x)))","-ID:\\Qt\\Tools\\QtCreator\\share\\qtcreator\\cplusplus\\wrappedMingwHeaders","-ID:\\Qt\\Tools\\QtCreator\\share\\qtcreator\\cplusplus\\wrappedQtHeaders","-ID:\\Qt\\Tools\\QtCreator\\share\\qtcreator\\cplusplus\\wrappedQtHeaders\\QtCore","-ID:\\embeddedprojectgithhub\\TIC_TAK_TOE_PROJECT\\final","-ID:\\Qt\\6.9.1\\mingw_64\\include","-ID:\\Qt\\6.9.1\\mingw_64\\include\\QtWidgets","-ID:\\Qt\\6.9.1\\mingw_64\\include\\QtGui","-ID:\\Qt\\6.9.1\\mingw_64\\include\\QtCore","-ID:\\embeddedprojectgithhub\\TIC_TAK_TOE_PROJECT\\final\\build\\Desktop_Qt_6_9_1_MinGW_64_bit-Release\\release","-ID:\\embeddedprojectgithhub\\TIC_TAK_TOE_PROJECT\\final\\build\\Desktop_Qt_6_9_1_MinGW_64_bit-Release","-ID:\\Qt\\6.9.1\\mingw_64\\mkspecs\\win32-g++","-isystem","D:\\Qt\\Tools\\mingw1310_64\\lib\\gcc\\x86_64-w64-mingw32\\13.1.0\\include\\c++","-isystem","D:\\Qt\\Tools\\mingw1310_64\\lib\\gcc\\x86_64-w64-mingw32\\13.1.0\\include\\c++\\x86_64-w64-mingw32","-isystem","D:\\Qt\\Tools\\mingw1310_64\\lib\\gcc\\x86_64-w64-mingw32\\13.1.0\\include\\c++\\backward","-isystem","D:\\Qt\\Tools\\QtCreator\\bin\\clang\\lib\\clang\\19\\include","-isystem","D:\\Qt\\Tools\\mingw1310_64\\x86_64-w64-mingw32\\include","-fmessage-length=0","-fdiagnostics-show-note-include-stack","-fretain-comments-from-system-headers","-fmacro-backtrace-limit=0","-ferror-limit=1000","-x","c++-header","D:\\embeddedprojectgithhub\\TIC_TAK_TOE_PROJECT\\final\\build\\Desktop_Qt_6_9_1_MinGW_64_bit-Release\\ui_login.h"],"directory":"D:/embeddedprojectgithhub/TIC_TAK_TOE_PROJECT/final/build/Desktop_Qt_6_9_1_MinGW_64_bit-Release/.qtc_clangd","file":"D:/embeddedprojectgithhub/TIC_TAK_TOE_PROJECT/final/build/Desktop_Qt_6_9_1_MinGW_64_bit-Release/ui_login.h"},{"arguments":["clang","-Wno-documentation-unknown-command","-Wno-unknown-warning-option","-Wno-unknown-pragmas","-nostdinc","-nostdinc++","-std=gnu++1z","-Wall","-Wextra","-Wextra","-fexceptions","-mthreads","-fsyntax-only","-m64","--target=x86_64-w64-mingw32","-DUNICODE","-D_UNICODE","-DWIN32","-DMINGW_HAS_SECURE_API","-DQT_NO_DEBUG","-DQT_WIDGETS_LIB","-DQT_GUI_LIB","-DQT_CORE_LIB","-DQT_NEEDS_QMAIN","-DQ_CREATOR_RUN","-DQT_ANNOTATE_FUNCTION(x)=__attribute__((annotate(#x)))","-ID:\\Qt\\Tools\\QtCreator\\share\\qtcreator\\cplusplus\\wrappedMingwHeaders","-ID:\\Qt\\Tools\\QtCreator\\share\\qtcreator\\cplusplus\\wrappedQtHeaders","-ID:\\Qt\\Tools\\QtCreator\\share\\qtcreator\\cplusplus\\wrappedQtHeaders\\QtCore","-ID:\\embeddedprojectgithhub\\TIC_TAK_TOE_PROJECT\\final","-ID:\\Qt\\6.9.1\\mingw_64\\include","-ID:\\Qt\\6.9.1\\mingw_64\\include\\QtWidgets","-ID:\\Qt\\6.9.1\\mingw_64\\include\\QtGui","-ID:\\Qt\\6.9.1\\mingw_64\\include\\QtCore","-ID:\\embeddedprojectgithhub\\TIC_TAK_TOE_PROJECT\\final\\build\\Desktop_Qt_6_9_1_MinGW_64_bit-Release\\release","-ID:\\embeddedprojectgithhub\\TIC_TAK_TOE_PROJECT\\final\\build\\Desktop_Qt_6_9_1_MinGW_64_bit-Release","-ID:\\Qt\\6.9.1\\mingw_64\\mkspecs\\win32-g++","-isystem","D:\\Qt\\Tools\\mingw1310_64\\lib\\gcc\\x86_64-w64-mingw32\\13.1.0\\include\\c++","-isystem","D:\\Qt\\Tools\\mingw1310_64\\lib\\gcc\\x86_64-w64-mingw32\\13.1.0\\include\\c++\\x86_64-w64-mingw32","-isystem","D:\\Qt\\Tools\\mingw1310_64\\lib\\gcc\\x86_64-w64-mingw32\\13.1.0\\include\\c++\\backward","-isystem","D:\\Qt\\Tools\\QtCreator\\bin\\clang\\lib\\clang\\19\\include","-isystem","D:\\Qt\\Tools\\mingw1310_64\\x86_64-w64-mingw32\\include","-fmessage-length=0","-fdiagnostics-show-note-include-stack","-fretain-comments-from-system-headers","-fmacro-backtrace-limit=0","-ferror-limit=1000","-x","c++-header","D:\\embeddedprojectgithhub\\TIC_TAK_TOE_PROJECT\\final\\build\\Desktop_Qt_6_9_1_MinGW_64_bit-Release\\ui_home.h"],"directory":"D:/embeddedprojectgithhub/TIC_TAK_TOE_PROJECT/final/build/Desktop_Qt_6_9_1_MinGW_64_bit-Release/.qtc_clangd","file":"D:/embeddedprojectgithhub/TIC_TAK_TOE_PROJECT/final/build/Desktop_Qt_6_9_1_MinGW_64_bit-Release/ui_home.h"},{"arguments":["clang","-Wno-documentation-unknown-command","-Wno-unknown-warning-option","-Wno-unknown-pragmas","-nostdinc","-nostdinc++","-std=gnu++1z","-Wall","-Wextra","-Wextra","-fexceptions","-mthreads","-fsyntax-only","-m64","--target=x86_64-w64-mingw32","-DUNICODE","-D_UNICODE","-DWIN32","-DMINGW_HAS_SECURE_API","-DQT_NO_DEBUG","-DQT_WIDGETS_LIB","-DQT_GUI_LIB","-DQT_CORE_LIB","-DQT_NEEDS_QMAIN","-DQ_CREATOR_RUN","-DQT_ANNOTATE_FUNCTION(x)=__attribute__((annotate(#x)))","-ID:\\Qt\\Tools\\QtCreator\\share\\qtcreator\\cplusplus\\wrappedMingwHeaders","-ID:\\Qt\\Tools\\QtCreator\\share\\qtcreator\\cplusplus\\wrappedQtHeaders","-ID:\\Qt\\Tools\\QtCreator\\share\\qtcreator\\cplusplus\\wrappedQtHeaders\\QtCore","-ID:\\embeddedprojectgithhub\\TIC_TAK_TOE_PROJECT\\final","-ID:\\Qt\\6.9.1\\mingw_64\\include","-ID:\\Qt\\6.9.1\\mingw_64\\include\\QtWidgets","-ID:\\Qt\\6.9.1\\mingw_64\\include\\QtGui","-ID:\\Qt\\6.9.1\\mingw_64\\include\\QtCore","-ID:\\embeddedprojectgithhub\\TIC_TAK_TOE_PROJECT\\final\\build\\Desktop_Qt_6_9_1_MinGW_64_bit-Release\\release","-ID:\\embeddedprojectgithhub\\TIC_TAK_TOE_PROJECT\\final\\build\\Desktop_Qt_6_9_1_MinGW_64_bit-Release","-ID:\\Qt\\6.9.1\\mingw_64\\mkspecs\\win32-g++","-isystem","D:\\Qt\\Tools\\mingw1310_64\\lib\\gcc\\x86_64-w64-mingw32\\13.1.0\\include\\c++","-isystem","D:\\Qt\\Tools\\mingw1310_64\\lib\\gcc\\x86_64-w64-mingw32\\13.1.0\\include\\c++\\x86_64-w64-mingw32","-isystem","D:\\Qt\\Tools\\mingw1310_64\\lib\\gcc\\x86_64-w64-mingw32\\13.1.0\\include\\c++\\backward","-isystem","D:\\Qt\\Tools\\QtCreator\\bin\\clang\\lib\\clang\\19\\include","-isystem","D:\\Qt\\Tools\\mingw1310_64\\x86_64-w64-mingw32\\include","-fmessage-length=0","-fdiagnostics-show-note-include-stack","-fretain-comments-from-system-headers","-fmacro-backtrace-limit=0","-ferror-limit=1000","-x","c++-header","D:\\embeddedprojectgithhub\\TIC_TAK_TOE_PROJECT\\final\\build\\Desktop_Qt_6_9_1_MinGW_64_bit-Release\\ui_mainwindow.h"],"directory":"D:/embeddedprojectgithhub/TIC_TAK_TOE_PROJECT/final/build/Desktop_Qt_6_9_1_MinGW_64_bit-Release/.qtc_clangd","file":"D:/embeddedprojectgithhub/TIC_TAK_TOE_PROJECT/final/build/Desktop_Qt_6_9_1_MinGW_64_bit-Release/ui_mainwindow.h"},{"arguments":["clang","-Wno-documentation-unknown-command","-Wno-unknown-warning-option","-Wno-unknown-pragmas","-nostdinc","-nostdinc++","-std=gnu++1z","-Wall","-Wextra","-Wextra","-fexceptions","-mthreads","-fsyntax-only","-m64","--target=x86_64-w64-mingw32","-DUNICODE","-D_UNICODE","-DWIN32","-DMINGW_HAS_SECURE_API","-DQT_NO_DEBUG","-DQT_WIDGETS_LIB","-DQT_GUI_LIB","-DQT_CORE_LIB","-DQT_NEEDS_QMAIN","-DQ_CREATOR_RUN","-DQT_ANNOTATE_FUNCTION(x)=__attribute__((annotate(#x)))","-ID:\\Qt\\Tools\\QtCreator\\share\\qtcreator\\cplusplus\\wrappedMingwHeaders","-ID:\\Qt\\Tools\\QtCreator\\share\\qtcreator\\cplusplus\\wrappedQtHeaders","-ID:\\Qt\\Tools\\QtCreator\\share\\qtcreator\\cplusplus\\wrappedQtHeaders\\QtCore","-ID:\\embeddedprojectgithhub\\TIC_TAK_TOE_PROJECT\\final","-ID:\\Qt\\6.9.1\\mingw_64\\include","-ID:\\Qt\\6.9.1\\mingw_64\\include\\QtWidgets","-ID:\\Qt\\6.9.1\\mingw_64\\include\\QtGui","-ID:\\Qt\\6.9.1\\mingw_64\\include\\QtCore","-ID:\\embeddedprojectgithhub\\TIC_TAK_TOE_PROJECT\\final\\build\\Desktop_Qt_6_9_1_MinGW_64_bit-Release\\release","-ID:\\embeddedprojectgithhub\\TIC_TAK_TOE_PROJECT\\final\\build\\Desktop_Qt_6_9_1_MinGW_64_bit-Release","-ID:\\Qt\\6.9.1\\mingw_64\\mkspecs\\win32-g++","-isystem","D:\\Qt\\Tools\\mingw1310_64\\lib\\gcc\\x86_64-w64-mingw32\\13.1.0\\include\\c++","-isystem","D:\\Qt\\Tools\\mingw1310_64\\lib\\gcc\\x86_64-w64-mingw32\\13.1.0\\include\\c++\\x86_64-w64-mingw32","-isystem","D:\\Qt\\Tools\\mingw1310_64\\lib\\gcc\\x86_64-w64-mingw32\\13.1.0\\include\\c++\\backward","-isystem","D:\\Qt\\Tools\\QtCreator\\bin\\clang\\lib\\clang\\19\\include","-isystem","D:\\Qt\\Tools\\mingw1310_64\\x86_64-w64-mingw32\\include","-fmessage-length=0","-fdiagnostics-show-note-include-stack","-fretain-comments-from-system-headers","-fmacro-backtrace-limit=0","-ferror-limit=1000","-x","c++-header","D:\\embeddedprojectgithhub\\TIC_TAK_TOE_PROJECT\\final\\build\\Desktop_Qt_6_9_1_MinGW_64_bit-Release\\ui_playboard.h"],"directory":"D:/embeddedprojectgithhub/TIC_TAK_TOE_PROJECT/final/build/Desktop_Qt_6_9_1_MinGW_64_bit-Release/.qtc_clangd","file":"D:/embeddedprojectgithhub/TIC_TAK_TOE_PROJECT/final/build/Desktop_Qt_6_9_1_MinGW_64_bit-Release/ui_playboard.h"},{"arguments":["clang","-Wno-documentation-unknown-command","-Wno-unknown-warning-option","-Wno-unknown-pragmas","-nostdinc","-nostdinc++","-std=gnu++1z","-Wall","-Wextra","-Wextra","-fexceptions","-mthreads","-fsyntax-only","-m64","--target=x86_64-w64-mingw32","-DUNICODE","-D_UNICODE","-DWIN32","-DMINGW_HAS_SECURE_API","-DQT_NO_DEBUG","-DQT_WIDGETS_LIB","-DQT_GUI_LIB","-DQT_CORE_LIB","-DQT_NEEDS_QMAIN","-DQ_CREATOR_RUN","-DQT_ANNOTATE_FUNCTION(x)=__attribute__((annotate(#x)))","-ID:\\Qt\\Tools\\QtCreator\\share\\qtcreator\\cplusplus\\wrappedMingwHeaders","-ID:\\Qt\\Tools\\QtCreator\\share\\qtcreator\\cplusplus\\wrappedQtHeaders","-ID:\\Qt\\Tools\\QtCreator\\share\\qtcreator\\cplusplus\\wrappedQtHeaders\\QtCore","-ID:\\embeddedprojectgithhub\\TIC_TAK_TOE_PROJECT\\final","-ID:\\Qt\\6.9.1\\mingw_64\\include","-ID:\\Qt\\6.9.1\\mingw_64\\include\\QtWidgets","-ID:\\Qt\\6.9.1\\mingw_64\\include\\QtGui","-ID:\\Qt\\6.9.1\\mingw_64\\include\\QtCore","-ID:\\embeddedprojectgithhub\\TIC_TAK_TOE_PROJECT\\final\\build\\Desktop_Qt_6_9_1_MinGW_64_bit-Release\\release","-ID:\\embeddedprojectgithhub\\TIC_TAK_TOE_PROJECT\\final\\build\\Desktop_Qt_6_9_1_MinGW_64_bit-Release","-ID:\\Qt\\6.9.1\\mingw_64\\mkspecs\\win32-g++","-isystem","D:\\Qt\\Tools\\mingw1310_64\\lib\\gcc\\x86_64-w64-mingw32\\13.1.0\\include\\c++","-isystem","D:\\Qt\\Tools\\mingw1310_64\\lib\\gcc\\x86_64-w64-mingw32\\13.1.0\\include\\c++\\x86_64-w64-mingw32","-isystem","D:\\Qt\\Tools\\mingw1310_64\\lib\\gcc\\x86_64-w64-mingw32\\13.1.0\\include\\c++\\backward","-isystem","D:\\Qt\\Tools\\QtCreator\\bin\\clang\\lib\\clang\\19\\include","-isystem","D:\\Qt\\Tools\\mingw1310_64\\x86_64-w64-mingw32\\include","-fmessage-length=0","-fdiagnostics-show-note-include-stack","-fretain-comments-from-system-headers","-fmacro-backtrace-limit=0","-ferror-limit=1000","-x","c++-header","D:\\embeddedprojectgithhub\\TIC_TAK_TOE_PROJECT\\final\\build\\Desktop_Qt_6_9_1_MinGW_64_bit-Release\\ui_replayboard.h"],"directory":"D:/embeddedprojectgithhub/TIC_TAK_TOE_PROJECT/final/build/Desktop_Qt_6_9_1_MinGW_64_bit-Release/.qtc_clangd","file":"D:/embeddedprojectgithhub/TIC_TAK_TOE_PROJECT/final/build/Desktop_Qt_6_9_1_MinGW_64_bit-Release/ui_replayboard.h"},{"arguments":["clang","-Wno-documentation-unknown-command","-Wno-unknown-warning-option","-Wno-unknown-pragmas","-nostdinc","-nostdinc++","-std=gnu++1z","-Wall","-Wextra","-Wextra","-fexceptions","-mthreads","-fsyntax-only","-m64","--target=x86_64-w64-mingw32","-DUNICODE","-D_UNICODE","-DWIN32","-DMINGW_HAS_SECURE_API","-DQT_NO_DEBUG","-DQT_WIDGETS_LIB","-DQT_GUI_LIB","-DQT_CORE_LIB","-DQT_NEEDS_QMAIN","-DQ_CREATOR_RUN","-DQT_ANNOTATE_FUNCTION(x)=__attribute__((annotate(#x)))","-ID:\\Qt\\Tools\\QtCreator\\share\\qtcreator\\cplusplus\\wrappedMingwHeaders","-ID:\\Qt\\Tools\\QtCreator\\share\\qtcreator\\cplusplus\\wrappedQtHeaders","-ID:\\Qt\\Tools\\QtCreator\\share\\qtcreator\\cplusplus\\wrappedQtHeaders\\QtCore","-ID:\\embeddedprojectgithhub\\TIC_TAK_TOE_PROJECT\\final","-ID:\\Qt\\6.9.1\\mingw_64\\include","-ID:\\Qt\\6.9.1\\mingw_64\\include\\QtWidgets","-ID:\\Qt\\6.9.1\\mingw_64\\include\\QtGui","-ID:\\Qt\\6.9.1\\mingw_64\\include\\QtCore","-ID:\\embeddedprojectgithhub\\TIC_TAK_TOE_PROJECT\\final\\build\\Desktop_Qt_6_9_1_MinGW_64_bit-Release\\release","-ID:\\embeddedprojectgithhub\\TIC_TAK_TOE_PROJECT\\final\\build\\Desktop_Qt_6_9_1_MinGW_64_bit-Release","-ID:\\Qt\\6.9.1\\mingw_64\\mkspecs\\win32-g++","-isystem","D:\\Qt\\Tools\\mingw1310_64\\lib\\gcc\\x86_64-w64-mingw32\\13.1.0\\include\\c++","-isystem","D:\\Qt\\Tools\\mingw1310_64\\lib\\gcc\\x86_64-w64-mingw32\\13.1.0\\include\\c++\\x86_64-w64-mingw32","-isystem","D:\\Qt\\Tools\\mingw1310_64\\lib\\gcc\\x86_64-w64-mingw32\\13.1.0\\include\\c++\\backward","-isystem","D:\\Qt\\Tools\\QtCreator\\bin\\clang\\lib\\clang\\19\\include","-isystem","D:\\Qt\\Tools\\mingw1310_64\\x86_64-w64-mingw32\\include","-fmessage-length=0","-fdiagnostics-show-note-include-stack","-fretain-comments-from-system-headers","-fmacro-backtrace-limit=0","-ferror-limit=1000","-x","c++-header","D:\\embeddedprojectgithhub\\TIC_TAK_TOE_PROJECT\\final\\build\\Desktop_Qt_6_9_1_MinGW_64_bit-Release\\ui_codeverification.h"],"directory":"D:/embeddedprojectgithhub/TIC_TAK_TOE_PROJECT/final/build/Desktop_Qt_6_9_1_MinGW_64_bit-Release/.qtc_clangd","file":"D:/embeddedprojectgithhub/TIC_TAK_TOE_PROJECT/final/build/Desktop_Qt_6_9_1_MinGW_64_bit-Release/ui_codeverification.h"}]